{"textures":{"0":"mineinabyss:mobs/kazura"},"elements":[{"from":[8.572719,7.900415,6.2941074],"to":[8.572719,8.6147,6.865536],"rotation":{"angle":45.0,"axis":"x","origin":[8.572719,8.328986,6.5798216]},"faces":{"east":{"uv":[6.0,4.5,6.25,4.8125],"rotation":0,"texture":"#0","tintindex":0},"south":{"uv":[0.0,0.0,0.0,0.3125],"rotation":0,"texture":"#0","tintindex":0},"north":{"uv":[0.0,0.0,0.0,0.3125],"rotation":0,"texture":"#0","tintindex":0},"west":{"uv":[4.75,6.0,5.0,6.3125],"rotation":0,"texture":"#0","tintindex":0},"up":{"uv":[0.0,0.25,0.0,0.0],"rotation":0,"texture":"#0","tintindex":0},"down":{"uv":[0.0,0.0,0.0,0.25],"rotation":0,"texture":"#0","tintindex":0}}},{"from":[7.858433,7.900415,5.15125],"to":[8.144147,8.043272,6.1512504],"rotation":{"angle":0.0,"axis":"y","origin":[5.715575,8.18613,6.0083933]},"faces":{"east":{"uv":[9.25,2.25,9.6875,2.3125],"rotation":0,"texture":"#0","tintindex":0},"south":{"uv":[3.25,9.75,3.375,9.8125],"rotation":0,"texture":"#0","tintindex":0},"north":{"uv":[9.75,3.0,9.875,3.0625],"rotation":0,"texture":"#0","tintindex":0},"west":{"uv":[2.5,9.25,2.9375,9.3125],"rotation":0,"texture":"#0","tintindex":0},"up":{"uv":[7.625,7.1875,7.5,6.75],"rotation":0,"texture":"#0","tintindex":0},"down":{"uv":[7.375,7.5,7.25,7.9375],"rotation":0,"texture":"#0","tintindex":0}}},{"from":[7.7155757,7.757558,6.1512504],"to":[8.287004,8.043272,7.1512504],"rotation":{"angle":0.0,"axis":"y","origin":[5.715575,8.18613,6.0083933]},"faces":{"east":{"uv":[7.5,7.5,7.9375,7.625],"rotation":0,"texture":"#0","tintindex":0},"south":{"uv":[4.5,8.5,4.75,8.625],"rotation":0,"texture":"#0","tintindex":0},"north":{"uv":[4.25,8.5,4.5,8.625],"rotation":0,"texture":"#0","tintindex":0},"west":{"uv":[0.0,7.75,0.4375,7.875],"rotation":0,"texture":"#0","tintindex":0},"up":{"uv":[4.75,5.6875,4.5,5.25],"rotation":0,"texture":"#0","tintindex":0},"down":{"uv":[5.0,5.25,4.75,5.6875],"rotation":0,"texture":"#0","tintindex":0}}},{"from":[8.144147,8.173003,5.8828673],"to":[8.572719,8.458718,6.454296],"rotation":{"angle":-45.0,"axis":"x","origin":[7.4298615,8.284172,6.126739]},"faces":{"east":{"uv":[4.75,8.5,5.0,8.625],"rotation":0,"texture":"#0","tintindex":0},"south":{"uv":[9.25,7.0,9.4375,7.125],"rotation":0,"texture":"#0","tintindex":0},"north":{"uv":[7.0,9.25,7.1875,9.375],"rotation":0,"texture":"#0","tintindex":0},"west":{"uv":[8.5,7.0,8.75,7.125],"rotation":0,"texture":"#0","tintindex":0},"up":{"uv":[4.9375,8.0,4.75,7.75],"rotation":0,"texture":"#0","tintindex":0},"down":{"uv":[7.9375,4.75,7.75,5.0],"rotation":0,"texture":"#0","tintindex":0}}},{"from":[9.00129,7.946901,10.218882],"to":[9.144147,8.089758,11.647453],"rotation":{"angle":0.0,"axis":"y","origin":[5.715575,8.18613,6.0083933]},"faces":{"east":{"uv":[4.75,8.0,5.375,8.0625],"rotation":0,"texture":"#0","tintindex":0},"south":{"uv":[6.75,9.75,6.8125,9.8125],"rotation":0,"texture":"#0","tintindex":0},"north":{"uv":[9.75,6.5,9.8125,6.5625],"rotation":0,"texture":"#0","tintindex":0},"west":{"uv":[8.0,4.75,8.625,4.8125],"rotation":0,"texture":"#0","tintindex":0},"up":{"uv":[5.5625,8.625,5.5,8.0],"rotation":0,"texture":"#0","tintindex":0},"down":{"uv":[5.8125,8.0,5.75,8.625],"rotation":0,"texture":"#0","tintindex":0}}},{"from":[9.00129,7.9738436,8.909336],"to":[9.144147,8.116701,10.337908],"rotation":{"angle":0.0,"axis":"y","origin":[5.715575,8.18613,6.0083933]},"faces":{"east":{"uv":[8.0,5.0,8.625,5.0625],"rotation":0,"texture":"#0","tintindex":0},"south":{"uv":[7.0,9.75,7.0625,9.8125],"rotation":0,"texture":"#0","tintindex":0},"north":{"uv":[9.75,6.75,9.8125,6.8125],"rotation":0,"texture":"#0","tintindex":0},"west":{"uv":[8.0,5.75,8.625,5.8125],"rotation":0,"texture":"#0","tintindex":0},"up":{"uv":[6.0625,8.625,6.0,8.0],"rotation":0,"texture":"#0","tintindex":0},"down":{"uv":[6.3125,8.0,6.25,8.625],"rotation":0,"texture":"#0","tintindex":0}}},{"from":[9.00129,7.900415,7.579822],"to":[9.287004,8.18613,9.008393],"rotation":{"angle":0.0,"axis":"y","origin":[5.715575,8.18613,6.0083933]},"faces":{"east":{"uv":[5.25,6.0,5.875,6.125],"rotation":0,"texture":"#0","tintindex":0},"south":{"uv":[1.25,9.5,1.375,9.625],"rotation":0,"texture":"#0","tintindex":0},"north":{"uv":[9.5,1.0,9.625,1.125],"rotation":0,"texture":"#0","tintindex":0},"west":{"uv":[6.0,5.5,6.625,5.625],"rotation":0,"texture":"#0","tintindex":0},"up":{"uv":[6.125,6.625,6.0,6.0],"rotation":0,"texture":"#0","tintindex":0},"down":{"uv":[0.625,6.25,0.5,6.875],"rotation":0,"texture":"#0","tintindex":0}}},{"from":[8.7400875,7.900415,6.6635046],"to":[9.025802,8.18613,7.8063617],"rotation":{"angle":45.0,"axis":"y","origin":[8.882944,8.328986,7.3777905]},"faces":{"east":{"uv":[7.0,6.75,7.5,6.875],"rotation":0,"texture":"#0","tintindex":0},"south":{"uv":[1.5,9.5,1.625,9.625],"rotation":0,"texture":"#0","tintindex":0},"north":{"uv":[9.5,1.25,9.625,1.375],"rotation":0,"texture":"#0","tintindex":0},"west":{"uv":[7.0,7.0,7.5,7.125],"rotation":0,"texture":"#0","tintindex":0},"up":{"uv":[0.125,7.75,0.0,7.25],"rotation":0,"texture":"#0","tintindex":0},"down":{"uv":[0.375,7.25,0.25,7.75],"rotation":0,"texture":"#0","tintindex":0}}},{"from":[6.858433,7.946901,10.218882],"to":[7.00129,8.089758,11.647453],"rotation":{"angle":0.0,"axis":"y","origin":[5.715575,8.18613,6.0083933]},"faces":{"east":{"uv":[8.0,6.0,8.625,6.0625],"rotation":0,"texture":"#0","tintindex":0},"south":{"uv":[7.25,9.75,7.3125,9.8125],"rotation":0,"texture":"#0","tintindex":0},"north":{"uv":[9.75,7.0,9.8125,7.0625],"rotation":0,"texture":"#0","tintindex":0},"west":{"uv":[8.0,6.25,8.625,6.3125],"rotation":0,"texture":"#0","tintindex":0},"up":{"uv":[6.5625,8.625,6.5,8.0],"rotation":0,"texture":"#0","tintindex":0},"down":{"uv":[6.8125,8.0,6.75,8.625],"rotation":0,"texture":"#0","tintindex":0}}},{"from":[6.858433,7.9738436,8.909336],"to":[7.00129,8.116701,10.337908],"rotation":{"angle":0.0,"axis":"y","origin":[5.715575,8.18613,6.0083933]},"faces":{"east":{"uv":[8.0,6.75,8.625,6.8125],"rotation":0,"texture":"#0","tintindex":0},"south":{"uv":[7.5,9.75,7.5625,9.8125],"rotation":0,"texture":"#0","tintindex":0},"north":{"uv":[9.75,7.25,9.8125,7.3125],"rotation":0,"texture":"#0","tintindex":0},"west":{"uv":[7.0,8.0,7.625,8.0625],"rotation":0,"texture":"#0","tintindex":0},"up":{"uv":[8.0625,7.625,8.0,7.0],"rotation":0,"texture":"#0","tintindex":0},"down":{"uv":[7.8125,8.0,7.75,8.625],"rotation":0,"texture":"#0","tintindex":0}}},{"from":[6.7155757,7.900415,7.579822],"to":[7.00129,8.18613,9.008393],"rotation":{"angle":0.0,"axis":"y","origin":[5.715575,8.18613,6.0083933]},"faces":{"east":{"uv":[6.25,0.0,6.875,0.125],"rotation":0,"texture":"#0","tintindex":0},"south":{"uv":[1.75,9.5,1.875,9.625],"rotation":0,"texture":"#0","tintindex":0},"north":{"uv":[9.5,1.5,9.625,1.625],"rotation":0,"texture":"#0","tintindex":0},"west":{"uv":[6.25,1.25,6.875,1.375],"rotation":0,"texture":"#0","tintindex":0},"up":{"uv":[0.875,6.875,0.75,6.25],"rotation":0,"texture":"#0","tintindex":0},"down":{"uv":[1.625,6.25,1.5,6.875],"rotation":0,"texture":"#0","tintindex":0}}},{"from":[6.9767785,7.900415,6.6635046],"to":[7.2624927,8.18613,7.8063617],"rotation":{"angle":-45.0,"axis":"y","origin":[7.1196356,8.328986,7.3777905]},"faces":{"east":{"uv":[7.25,0.25,7.75,0.375],"rotation":0,"texture":"#0","tintindex":0},"south":{"uv":[2.0,9.5,2.125,9.625],"rotation":0,"texture":"#0","tintindex":0},"north":{"uv":[9.5,1.75,9.625,1.875],"rotation":0,"texture":"#0","tintindex":0},"west":{"uv":[7.25,0.5,7.75,0.625],"rotation":0,"texture":"#0","tintindex":0},"up":{"uv":[7.375,1.25,7.25,0.75],"rotation":0,"texture":"#0","tintindex":0},"down":{"uv":[1.125,7.25,1.0,7.75],"rotation":0,"texture":"#0","tintindex":0}}},{"from":[7.7155757,7.946901,10.647453],"to":[7.858433,8.089758,12.076025],"rotation":{"angle":0.0,"axis":"y","origin":[5.715575,8.18613,6.0083933]},"faces":{"east":{"uv":[8.0,7.75,8.625,7.8125],"rotation":0,"texture":"#0","tintindex":0},"south":{"uv":[7.75,9.75,7.8125,9.8125],"rotation":0,"texture":"#0","tintindex":0},"north":{"uv":[9.75,7.5,9.8125,7.5625],"rotation":0,"texture":"#0","tintindex":0},"west":{"uv":[8.0,8.0,8.625,8.0625],"rotation":0,"texture":"#0","tintindex":0},"up":{"uv":[0.0625,8.875,0.0,8.25],"rotation":0,"texture":"#0","tintindex":0},"down":{"uv":[8.3125,0.0,8.25,0.625],"rotation":0,"texture":"#0","tintindex":0}}},{"from":[7.7155757,7.9738436,9.337908],"to":[7.858433,8.116701,10.7664795],"rotation":{"angle":0.0,"axis":"y","origin":[5.715575,8.18613,6.0083933]},"faces":{"east":{"uv":[0.25,8.25,0.875,8.3125],"rotation":0,"texture":"#0","tintindex":0},"south":{"uv":[8.0,9.75,8.0625,9.8125],"rotation":0,"texture":"#0","tintindex":0},"north":{"uv":[9.75,7.75,9.8125,7.8125],"rotation":0,"texture":"#0","tintindex":0},"west":{"uv":[8.25,0.75,8.875,0.8125],"rotation":0,"texture":"#0","tintindex":0},"up":{"uv":[1.0625,8.875,1.0,8.25],"rotation":0,"texture":"#0","tintindex":0},"down":{"uv":[1.3125,8.25,1.25,8.875],"rotation":0,"texture":"#0","tintindex":0}}},{"from":[7.5727186,7.900415,8.008393],"to":[7.858433,8.18613,9.436965],"rotation":{"angle":0.0,"axis":"y","origin":[5.715575,8.18613,6.0083933]},"faces":{"east":{"uv":[6.25,1.5,6.875,1.625],"rotation":0,"texture":"#0","tintindex":0},"south":{"uv":[2.25,9.5,2.375,9.625],"rotation":0,"texture":"#0","tintindex":0},"north":{"uv":[9.5,2.0,9.625,2.125],"rotation":0,"texture":"#0","tintindex":0},"west":{"uv":[1.75,6.25,2.375,6.375],"rotation":0,"texture":"#0","tintindex":0},"up":{"uv":[6.375,2.375,6.25,1.75],"rotation":0,"texture":"#0","tintindex":0},"down":{"uv":[2.625,6.25,2.5,6.875],"rotation":0,"texture":"#0","tintindex":0}}},{"from":[7.5727186,7.900415,7.0083933],"to":[7.858433,8.18613,8.151251],"rotation":{"angle":0.0,"axis":"y","origin":[5.715575,8.18613,6.0083933]},"faces":{"east":{"uv":[1.25,7.25,1.75,7.375],"rotation":0,"texture":"#0","tintindex":0},"south":{"uv":[2.75,9.5,2.875,9.625],"rotation":0,"texture":"#0","tintindex":0},"north":{"uv":[2.5,9.5,2.625,9.625],"rotation":0,"texture":"#0","tintindex":0},"west":{"uv":[1.75,7.25,2.25,7.375],"rotation":0,"texture":"#0","tintindex":0},"up":{"uv":[7.375,2.25,7.25,1.75],"rotation":0,"texture":"#0","tintindex":0},"down":{"uv":[7.375,2.25,7.25,2.75],"rotation":0,"texture":"#0","tintindex":0}}},{"from":[7.7155757,7.089758,10.218882],"to":[7.858433,7.232615,11.647453],"rotation":{"angle":0.0,"axis":"y","origin":[5.715575,8.18613,6.0083933]},"faces":{"east":{"uv":[8.25,1.0,8.875,1.0625],"rotation":0,"texture":"#0","tintindex":0},"south":{"uv":[8.25,9.75,8.3125,9.8125],"rotation":0,"texture":"#0","tintindex":0},"north":{"uv":[9.75,8.0,9.8125,8.0625],"rotation":0,"texture":"#0","tintindex":0},"west":{"uv":[1.5,8.25,2.125,8.3125],"rotation":0,"texture":"#0","tintindex":0},"up":{"uv":[2.3125,8.875,2.25,8.25],"rotation":0,"texture":"#0","tintindex":0},"down":{"uv":[2.5625,8.25,2.5,8.875],"rotation":0,"texture":"#0","tintindex":0}}},{"from":[7.7155757,7.1167006,8.909336],"to":[7.858433,7.2595577,10.337908],"rotation":{"angle":0.0,"axis":"y","origin":[5.715575,8.18613,6.0083933]},"faces":{"east":{"uv":[8.25,1.75,8.875,1.8125],"rotation":0,"texture":"#0","tintindex":0},"south":{"uv":[8.5,9.75,8.5625,9.8125],"rotation":0,"texture":"#0","tintindex":0},"north":{"uv":[9.75,8.25,9.8125,8.3125],"rotation":0,"texture":"#0","tintindex":0},"west":{"uv":[8.25,2.0,8.875,2.0625],"rotation":0,"texture":"#0","tintindex":0},"up":{"uv":[8.3125,3.125,8.25,2.5],"rotation":0,"texture":"#0","tintindex":0},"down":{"uv":[2.8125,8.25,2.75,8.875],"rotation":0,"texture":"#0","tintindex":0}}},{"from":[7.5727186,7.043272,7.579822],"to":[7.858433,7.328986,9.008393],"rotation":{"angle":0.0,"axis":"y","origin":[5.715575,8.18613,6.0083933]},"faces":{"east":{"uv":[6.25,2.5,6.875,2.625],"rotation":0,"texture":"#0","tintindex":0},"south":{"uv":[3.25,9.5,3.375,9.625],"rotation":0,"texture":"#0","tintindex":0},"north":{"uv":[3.0,9.5,3.125,9.625],"rotation":0,"texture":"#0","tintindex":0},"west":{"uv":[6.25,2.75,6.875,2.875],"rotation":0,"texture":"#0","tintindex":0},"up":{"uv":[2.875,6.875,2.75,6.25],"rotation":0,"texture":"#0","tintindex":0},"down":{"uv":[3.375,6.25,3.25,6.875],"rotation":0,"texture":"#0","tintindex":0}}},{"from":[7.5727186,7.220792,6.865536],"to":[7.858433,7.5065064,8.008393],"rotation":{"angle":45.0,"axis":"x","origin":[8.00129,7.6493635,7.579822]},"faces":{"east":{"uv":[7.25,2.75,7.75,2.875],"rotation":0,"texture":"#0","tintindex":0},"south":{"uv":[3.75,9.5,3.875,9.625],"rotation":0,"texture":"#0","tintindex":0},"north":{"uv":[3.5,9.5,3.625,9.625],"rotation":0,"texture":"#0","tintindex":0},"west":{"uv":[3.0,7.25,3.5,7.375],"rotation":0,"texture":"#0","tintindex":0},"up":{"uv":[3.625,7.75,3.5,7.25],"rotation":0,"texture":"#0","tintindex":0},"down":{"uv":[7.375,3.75,7.25,4.25],"rotation":0,"texture":"#0","tintindex":0}}},{"from":[8.144147,7.089758,10.218882],"to":[8.287004,7.232615,11.647453],"rotation":{"angle":0.0,"axis":"y","origin":[5.715575,8.18613,6.0083933]},"faces":{"east":{"uv":[3.0,8.25,3.625,8.3125],"rotation":0,"texture":"#0","tintindex":0},"south":{"uv":[8.75,9.75,8.8125,9.8125],"rotation":0,"texture":"#0","tintindex":0},"north":{"uv":[9.75,8.5,9.8125,8.5625],"rotation":0,"texture":"#0","tintindex":0},"west":{"uv":[8.25,3.25,8.875,3.3125],"rotation":0,"texture":"#0","tintindex":0},"up":{"uv":[3.8125,8.875,3.75,8.25],"rotation":0,"texture":"#0","tintindex":0},"down":{"uv":[4.0625,8.25,4.0,8.875],"rotation":0,"texture":"#0","tintindex":0}}},{"from":[8.144147,7.1167006,8.909336],"to":[8.287004,7.2595577,10.337908],"rotation":{"angle":0.0,"axis":"y","origin":[5.715575,8.18613,6.0083933]},"faces":{"east":{"uv":[8.25,4.0,8.875,4.0625],"rotation":0,"texture":"#0","tintindex":0},"south":{"uv":[9.0,9.75,9.0625,9.8125],"rotation":0,"texture":"#0","tintindex":0},"north":{"uv":[9.75,8.75,9.8125,8.8125],"rotation":0,"texture":"#0","tintindex":0},"west":{"uv":[4.25,8.25,4.875,8.3125],"rotation":0,"texture":"#0","tintindex":0},"up":{"uv":[5.0625,8.875,5.0,8.25],"rotation":0,"texture":"#0","tintindex":0},"down":{"uv":[5.3125,8.25,5.25,8.875],"rotation":0,"texture":"#0","tintindex":0}}},{"from":[8.144147,7.043272,7.579822],"to":[8.429861,7.328986,9.008393],"rotation":{"angle":0.0,"axis":"y","origin":[5.715575,8.18613,6.0083933]},"faces":{"east":{"uv":[6.25,3.0,6.875,3.125],"rotation":0,"texture":"#0","tintindex":0},"south":{"uv":[4.25,9.5,4.375,9.625],"rotation":0,"texture":"#0","tintindex":0},"north":{"uv":[4.0,9.5,4.125,9.625],"rotation":0,"texture":"#0","tintindex":0},"west":{"uv":[3.5,6.25,4.125,6.375],"rotation":0,"texture":"#0","tintindex":0},"up":{"uv":[6.375,4.375,6.25,3.75],"rotation":0,"texture":"#0","tintindex":0},"down":{"uv":[6.375,4.5,6.25,5.125],"rotation":0,"texture":"#0","tintindex":0}}},{"from":[8.144147,7.220792,6.865536],"to":[8.429861,7.5065064,8.008393],"rotation":{"angle":45.0,"axis":"x","origin":[8.00129,7.6493635,7.579822]},"faces":{"east":{"uv":[4.25,7.25,4.75,7.375],"rotation":0,"texture":"#0","tintindex":0},"south":{"uv":[4.75,9.5,4.875,9.625],"rotation":0,"texture":"#0","tintindex":0},"north":{"uv":[4.5,9.5,4.625,9.625],"rotation":0,"texture":"#0","tintindex":0},"west":{"uv":[7.25,4.25,7.75,4.375],"rotation":0,"texture":"#0","tintindex":0},"up":{"uv":[7.375,5.0,7.25,4.5],"rotation":0,"texture":"#0","tintindex":0},"down":{"uv":[4.875,7.25,4.75,7.75],"rotation":0,"texture":"#0","tintindex":0}}},{"from":[8.144147,7.946901,10.647453],"to":[8.287004,8.089758,12.076025],"rotation":{"angle":0.0,"axis":"y","origin":[5.715575,8.18613,6.0083933]},"faces":{"east":{"uv":[8.25,4.25,8.875,4.3125],"rotation":0,"texture":"#0","tintindex":0},"south":{"uv":[9.25,9.75,9.3125,9.8125],"rotation":0,"texture":"#0","tintindex":0},"north":{"uv":[9.75,9.0,9.8125,9.0625],"rotation":0,"texture":"#0","tintindex":0},"west":{"uv":[8.25,4.5,8.875,4.5625],"rotation":0,"texture":"#0","tintindex":0},"up":{"uv":[7.0625,8.875,7.0,8.25],"rotation":0,"texture":"#0","tintindex":0},"down":{"uv":[8.3125,7.0,8.25,7.625],"rotation":0,"texture":"#0","tintindex":0}}},{"from":[8.144147,7.9738436,9.337908],"to":[8.287004,8.116701,10.7664795],"rotation":{"angle":0.0,"axis":"y","origin":[5.715575,8.18613,6.0083933]},"faces":{"east":{"uv":[8.25,5.25,8.875,5.3125],"rotation":0,"texture":"#0","tintindex":0},"south":{"uv":[9.5,9.75,9.5625,9.8125],"rotation":0,"texture":"#0","tintindex":0},"north":{"uv":[9.75,9.25,9.8125,9.3125],"rotation":0,"texture":"#0","tintindex":0},"west":{"uv":[8.25,5.5,8.875,5.5625],"rotation":0,"texture":"#0","tintindex":0},"up":{"uv":[7.3125,8.875,7.25,8.25],"rotation":0,"texture":"#0","tintindex":0},"down":{"uv":[7.5625,8.25,7.5,8.875],"rotation":0,"texture":"#0","tintindex":0}}},{"from":[8.144147,7.900415,8.008393],"to":[8.429861,8.18613,9.436965],"rotation":{"angle":0.0,"axis":"y","origin":[5.715575,8.18613,6.0083933]},"faces":{"east":{"uv":[5.0,6.25,5.625,6.375],"rotation":0,"texture":"#0","tintindex":0},"south":{"uv":[5.25,9.5,5.375,9.625],"rotation":0,"texture":"#0","tintindex":0},"north":{"uv":[5.0,9.5,5.125,9.625],"rotation":0,"texture":"#0","tintindex":0},"west":{"uv":[6.25,5.25,6.875,5.375],"rotation":0,"texture":"#0","tintindex":0},"up":{"uv":[5.875,6.875,5.75,6.25],"rotation":0,"texture":"#0","tintindex":0},"down":{"uv":[6.375,5.75,6.25,6.375],"rotation":0,"texture":"#0","tintindex":0}}},{"from":[8.144147,7.900415,7.0083933],"to":[8.429861,8.18613,8.151251],"rotation":{"angle":0.0,"axis":"y","origin":[5.715575,8.18613,6.0083933]},"faces":{"east":{"uv":[7.25,5.0,7.75,5.125],"rotation":0,"texture":"#0","tintindex":0},"south":{"uv":[5.75,9.5,5.875,9.625],"rotation":0,"texture":"#0","tintindex":0},"north":{"uv":[5.5,9.5,5.625,9.625],"rotation":0,"texture":"#0","tintindex":0},"west":{"uv":[5.25,7.25,5.75,7.375],"rotation":0,"texture":"#0","tintindex":0},"up":{"uv":[5.875,7.75,5.75,7.25],"rotation":0,"texture":"#0","tintindex":0},"down":{"uv":[6.125,7.25,6.0,7.75],"rotation":0,"texture":"#0","tintindex":0}}},{"from":[8.287004,8.375472,10.933167],"to":[8.429861,8.51833,12.361739],"rotation":{"angle":0.0,"axis":"y","origin":[5.715575,8.18613,6.0083933]},"faces":{"east":{"uv":[8.25,6.5,8.875,6.5625],"rotation":0,"texture":"#0","tintindex":0},"south":{"uv":[9.75,9.75,9.8125,9.8125],"rotation":0,"texture":"#0","tintindex":0},"north":{"uv":[9.75,9.5,9.8125,9.5625],"rotation":0,"texture":"#0","tintindex":0},"west":{"uv":[8.0,8.25,8.625,8.3125],"rotation":0,"texture":"#0","tintindex":0},"up":{"uv":[8.5625,0.625,8.5,0.0],"rotation":0,"texture":"#0","tintindex":0},"down":{"uv":[0.3125,8.5,0.25,9.125],"rotation":0,"texture":"#0","tintindex":0}}},{"from":[8.287004,8.402415,9.623622],"to":[8.429861,8.545272,11.052194],"rotation":{"angle":0.0,"axis":"y","origin":[5.715575,8.18613,6.0083933]},"faces":{"east":{"uv":[8.5,1.25,9.125,1.3125],"rotation":0,"texture":"#0","tintindex":0},"south":{"uv":[10.0,0.0,10.0625,0.0625],"rotation":0,"texture":"#0","tintindex":0},"north":{"uv":[0.0,10.0,0.0625,10.0625],"rotation":0,"texture":"#0","tintindex":0},"west":{"uv":[1.5,8.5,2.125,8.5625],"rotation":0,"texture":"#0","tintindex":0},"up":{"uv":[0.5625,9.125,0.5,8.5],"rotation":0,"texture":"#0","tintindex":0},"down":{"uv":[0.8125,8.5,0.75,9.125],"rotation":0,"texture":"#0","tintindex":0}}},{"from":[8.287004,8.328986,8.294107],"to":[8.572719,8.6147,9.722679],"rotation":{"angle":0.0,"axis":"y","origin":[5.715575,8.18613,6.0083933]},"faces":{"east":{"uv":[6.5,0.25,7.125,0.375],"rotation":0,"texture":"#0","tintindex":0},"south":{"uv":[6.25,9.5,6.375,9.625],"rotation":0,"texture":"#0","tintindex":0},"north":{"uv":[6.0,9.5,6.125,9.625],"rotation":0,"texture":"#0","tintindex":0},"west":{"uv":[6.5,0.5,7.125,0.625],"rotation":0,"texture":"#0","tintindex":0},"up":{"uv":[0.125,7.125,0.0,6.5],"rotation":0,"texture":"#0","tintindex":0},"down":{"uv":[0.375,6.5,0.25,7.125],"rotation":0,"texture":"#0","tintindex":0}}},{"from":[8.287004,8.328986,7.2941074],"to":[8.572719,8.6147,8.436965],"rotation":{"angle":0.0,"axis":"y","origin":[5.715575,8.18613,6.0083933]},"faces":{"east":{"uv":[6.25,7.25,6.75,7.375],"rotation":0,"texture":"#0","tintindex":0},"south":{"uv":[6.75,9.5,6.875,9.625],"rotation":0,"texture":"#0","tintindex":0},"north":{"uv":[6.5,9.5,6.625,9.625],"rotation":0,"texture":"#0","tintindex":0},"west":{"uv":[7.25,6.25,7.75,6.375],"rotation":0,"texture":"#0","tintindex":0},"up":{"uv":[6.875,7.75,6.75,7.25],"rotation":0,"texture":"#0","tintindex":0},"down":{"uv":[7.125,7.25,7.0,7.75],"rotation":0,"texture":"#0","tintindex":0}}},{"from":[7.5727186,8.375472,10.933167],"to":[7.7155757,8.51833,12.361739],"rotation":{"angle":0.0,"axis":"y","origin":[5.715575,8.18613,6.0083933]},"faces":{"east":{"uv":[8.5,1.5,9.125,1.5625],"rotation":0,"texture":"#0","tintindex":0},"south":{"uv":[10.0,0.25,10.0625,0.3125],"rotation":0,"texture":"#0","tintindex":0},"north":{"uv":[0.25,10.0,0.3125,10.0625],"rotation":0,"texture":"#0","tintindex":0},"west":{"uv":[8.5,2.25,9.125,2.3125],"rotation":0,"texture":"#0","tintindex":0},"up":{"uv":[8.5625,3.125,8.5,2.5],"rotation":0,"texture":"#0","tintindex":0},"down":{"uv":[3.0625,8.5,3.0,9.125],"rotation":0,"texture":"#0","tintindex":0}}},{"from":[7.5727186,8.402415,9.623622],"to":[7.7155757,8.545272,11.052194],"rotation":{"angle":0.0,"axis":"y","origin":[5.715575,8.18613,6.0083933]},"faces":{"east":{"uv":[8.5,3.5,9.125,3.5625],"rotation":0,"texture":"#0","tintindex":0},"south":{"uv":[10.0,0.5,10.0625,0.5625],"rotation":0,"texture":"#0","tintindex":0},"north":{"uv":[0.5,10.0,0.5625,10.0625],"rotation":0,"texture":"#0","tintindex":0},"west":{"uv":[8.5,3.75,9.125,3.8125],"rotation":0,"texture":"#0","tintindex":0},"up":{"uv":[3.3125,9.125,3.25,8.5],"rotation":0,"texture":"#0","tintindex":0},"down":{"uv":[3.5625,8.5,3.5,9.125],"rotation":0,"texture":"#0","tintindex":0}}},{"from":[7.4298615,8.328986,8.294107],"to":[7.7155757,8.6147,9.722679],"rotation":{"angle":0.0,"axis":"y","origin":[5.715575,8.18613,6.0083933]},"faces":{"east":{"uv":[6.5,0.75,7.125,0.875],"rotation":0,"texture":"#0","tintindex":0},"south":{"uv":[9.5,7.0,9.625,7.125],"rotation":0,"texture":"#0","tintindex":0},"north":{"uv":[7.0,9.5,7.125,9.625],"rotation":0,"texture":"#0","tintindex":0},"west":{"uv":[6.5,1.0,7.125,1.125],"rotation":0,"texture":"#0","tintindex":0},"up":{"uv":[1.125,7.125,1.0,6.5],"rotation":0,"texture":"#0","tintindex":0},"down":{"uv":[1.375,6.5,1.25,7.125],"rotation":0,"texture":"#0","tintindex":0}}},{"from":[7.4298615,8.328986,7.2941074],"to":[7.7155757,8.6147,8.436965],"rotation":{"angle":0.0,"axis":"y","origin":[5.715575,8.18613,6.0083933]},"faces":{"east":{"uv":[7.25,7.25,7.75,7.375],"rotation":0,"texture":"#0","tintindex":0},"south":{"uv":[9.5,7.25,9.625,7.375],"rotation":0,"texture":"#0","tintindex":0},"north":{"uv":[7.25,9.5,7.375,9.625],"rotation":0,"texture":"#0","tintindex":0},"west":{"uv":[0.5,7.5,1.0,7.625],"rotation":0,"texture":"#0","tintindex":0},"up":{"uv":[7.625,1.25,7.5,0.75],"rotation":0,"texture":"#0","tintindex":0},"down":{"uv":[1.375,7.5,1.25,8.0],"rotation":0,"texture":"#0","tintindex":0}}},{"from":[7.4298615,8.173003,5.8828673],"to":[7.858433,8.458718,6.454296],"rotation":{"angle":-45.0,"axis":"x","origin":[8.572719,8.284172,6.126739]},"faces":{"east":{"uv":[8.5,7.25,8.75,7.375],"rotation":0,"texture":"#0","tintindex":0},"south":{"uv":[9.25,7.25,9.4375,7.375],"rotation":0,"texture":"#0","tintindex":0},"north":{"uv":[7.25,9.25,7.4375,9.375],"rotation":0,"texture":"#0","tintindex":0},"west":{"uv":[8.5,7.5,8.75,7.625],"rotation":0,"texture":"#0","tintindex":0},"up":{"uv":[5.1875,8.0,5.0,7.75],"rotation":0,"texture":"#0","tintindex":0},"down":{"uv":[7.9375,5.0,7.75,5.25],"rotation":0,"texture":"#0","tintindex":0}}},{"from":[7.2870045,8.3534975,6.2349334],"to":[8.715576,8.639212,6.8063617],"rotation":{"angle":0.0,"axis":"y","origin":[5.715575,8.18613,6.0083933]},"faces":{"east":{"uv":[8.0,8.5,8.25,8.625],"rotation":0,"texture":"#0","tintindex":0},"south":{"uv":[6.5,1.75,7.125,1.875],"rotation":0,"texture":"#0","tintindex":0},"north":{"uv":[1.75,6.5,2.375,6.625],"rotation":0,"texture":"#0","tintindex":0},"west":{"uv":[8.25,8.5,8.5,8.625],"rotation":0,"texture":"#0","tintindex":0},"up":{"uv":[3.875,0.75,3.25,0.5],"rotation":0,"texture":"#0","tintindex":0},"down":{"uv":[3.875,0.75,3.25,1.0],"rotation":0,"texture":"#0","tintindex":0}}},{"from":[7.2870045,8.360675,5.7645216],"to":[8.715576,8.646389,6.6216645],"rotation":{"angle":-45.0,"axis":"x","origin":[8.858433,9.6147,6.2941074]},"faces":{"east":{"uv":[5.25,7.75,5.625,7.875],"rotation":0,"texture":"#0","tintindex":0},"south":{"uv":[6.5,2.25,7.125,2.375],"rotation":0,"texture":"#0","tintindex":0},"north":{"uv":[6.5,2.0,7.125,2.125],"rotation":0,"texture":"#0","tintindex":0},"west":{"uv":[7.75,5.25,8.125,5.375],"rotation":0,"texture":"#0","tintindex":0},"up":{"uv":[2.125,1.375,1.5,1.0],"rotation":0,"texture":"#0","tintindex":0},"down":{"uv":[2.125,1.5,1.5,1.875],"rotation":0,"texture":"#0","tintindex":0}}},{"from":[7.4298615,7.900415,6.2941074],"to":[7.4298615,8.6147,6.865536],"rotation":{"angle":45.0,"axis":"x","origin":[7.4298615,8.328986,6.5798216]},"faces":{"east":{"uv":[3.0,6.5,3.25,6.8125],"rotation":0,"texture":"#0","tintindex":0},"south":{"uv":[0.0,0.0,0.0,0.3125],"rotation":0,"texture":"#0","tintindex":0},"north":{"uv":[0.0,0.0,0.0,0.3125],"rotation":0,"texture":"#0","tintindex":0},"west":{"uv":[6.5,3.25,6.75,3.5625],"rotation":0,"texture":"#0","tintindex":0},"up":{"uv":[0.0,0.25,0.0,0.0],"rotation":0,"texture":"#0","tintindex":0},"down":{"uv":[0.0,0.0,0.0,0.25],"rotation":0,"texture":"#0","tintindex":0}}},{"from":[7.858433,8.900415,5.5798216],"to":[8.144147,9.043272,6.1512504],"rotation":{"angle":0.0,"axis":"y","origin":[5.715575,8.18613,6.0083933]},"faces":{"east":{"uv":[7.5,9.5,7.75,9.5625],"rotation":0,"texture":"#0","tintindex":0},"south":{"uv":[3.5,9.75,3.625,9.8125],"rotation":0,"texture":"#0","tintindex":0},"north":{"uv":[9.75,3.25,9.875,3.3125],"rotation":0,"texture":"#0","tintindex":0},"west":{"uv":[9.5,7.5,9.75,7.5625],"rotation":0,"texture":"#0","tintindex":0},"up":{"uv":[8.625,8.75,8.5,8.5],"rotation":0,"texture":"#0","tintindex":0},"down":{"uv":[8.875,0.0,8.75,0.25],"rotation":0,"texture":"#0","tintindex":0}}},{"from":[7.7155757,9.043272,6.1512504],"to":[8.287004,9.18613,7.1512504],"rotation":{"angle":0.0,"axis":"y","origin":[5.715575,8.18613,6.0083933]},"faces":{"east":{"uv":[9.25,2.5,9.6875,2.5625],"rotation":0,"texture":"#0","tintindex":0},"south":{"uv":[9.5,7.75,9.75,7.8125],"rotation":0,"texture":"#0","tintindex":0},"north":{"uv":[7.75,9.5,8.0,9.5625],"rotation":0,"texture":"#0","tintindex":0},"west":{"uv":[9.25,2.75,9.6875,2.8125],"rotation":0,"texture":"#0","tintindex":0},"up":{"uv":[5.25,5.6875,5.0,5.25],"rotation":0,"texture":"#0","tintindex":0},"down":{"uv":[5.5,5.25,5.25,5.6875],"rotation":0,"texture":"#0","tintindex":0}}},{"from":[7.7155757,8.043272,6.2941074],"to":[8.287004,8.6147,7.1512504],"rotation":{"angle":0.0,"axis":"y","origin":[5.715575,8.18613,6.0083933]},"faces":{"east":{"uv":[5.5,5.5,5.875,5.75],"rotation":0,"texture":"#0","tintindex":0},"south":{"uv":[1.75,7.5,2.0,7.75],"rotation":0,"texture":"#0","tintindex":0},"north":{"uv":[1.5,7.5,1.75,7.75],"rotation":0,"texture":"#0","tintindex":0},"west":{"uv":[5.75,0.0,6.125,0.25],"rotation":0,"texture":"#0","tintindex":0},"up":{"uv":[6.0,0.625,5.75,0.25],"rotation":0,"texture":"#0","tintindex":0},"down":{"uv":[6.0,0.75,5.75,1.125],"rotation":0,"texture":"#0","tintindex":0}}},{"from":[7.5727186,8.328986,6.2941074],"to":[8.429861,8.900415,7.4369645],"rotation":{"angle":0.0,"axis":"y","origin":[5.715575,8.18613,6.0083933]},"faces":{"east":{"uv":[2.0,4.75,2.5,5.0],"rotation":0,"texture":"#0","tintindex":0},"south":{"uv":[5.75,1.5,6.125,1.75],"rotation":0,"texture":"#0","tintindex":0},"north":{"uv":[5.75,1.25,6.125,1.5],"rotation":0,"texture":"#0","tintindex":0},"west":{"uv":[4.75,2.0,5.25,2.25],"rotation":0,"texture":"#0","tintindex":0},"up":{"uv":[3.125,0.5,2.75,0.0],"rotation":0,"texture":"#0","tintindex":0},"down":{"uv":[3.125,0.5,2.75,1.0],"rotation":0,"texture":"#0","tintindex":0}}},{"from":[7.4298615,8.471844,6.0083933],"to":[8.572719,9.043272,7.1512504],"rotation":{"angle":0.0,"axis":"y","origin":[5.715575,8.18613,6.0083933]},"faces":{"east":{"uv":[2.5,4.75,3.0,5.0],"rotation":0,"texture":"#0","tintindex":0},"south":{"uv":[4.75,2.5,5.25,2.75],"rotation":0,"texture":"#0","tintindex":0},"north":{"uv":[4.75,2.25,5.25,2.5],"rotation":0,"texture":"#0","tintindex":0},"west":{"uv":[4.75,2.75,5.25,3.0],"rotation":0,"texture":"#0","tintindex":0},"up":{"uv":[0.5,0.5,0.0,0.0],"rotation":0,"texture":"#0","tintindex":0},"down":{"uv":[0.5,0.5,0.0,1.0],"rotation":0,"texture":"#0","tintindex":0}}},{"from":[7.7155757,8.043272,5.15125],"to":[8.287004,8.6147,5.4369645],"rotation":{"angle":0.0,"axis":"y","origin":[5.715575,8.18613,6.0083933]},"faces":{"east":{"uv":[8.75,0.25,8.875,0.5],"rotation":0,"texture":"#0","tintindex":0},"south":{"uv":[2.0,7.5,2.25,7.75],"rotation":0,"texture":"#0","tintindex":0},"north":{"uv":[7.5,1.75,7.75,2.0],"rotation":0,"texture":"#0","tintindex":0},"west":{"uv":[8.75,0.5,8.875,0.75],"rotation":0,"texture":"#0","tintindex":0},"up":{"uv":[1.75,8.875,1.5,8.75],"rotation":0,"texture":"#0","tintindex":0},"down":{"uv":[2.0,8.75,1.75,8.875],"rotation":0,"texture":"#0","tintindex":0}}},{"from":[7.5727186,8.043272,5.4369645],"to":[8.429861,8.900415,6.2941074],"rotation":{"angle":0.0,"axis":"y","origin":[5.715575,8.18613,6.0083933]},"faces":{"east":{"uv":[3.5,3.0,3.875,3.375],"rotation":0,"texture":"#0","tintindex":0},"south":{"uv":[3.5,3.5,3.875,3.875],"rotation":0,"texture":"#0","tintindex":0},"north":{"uv":[3.0,3.5,3.375,3.875],"rotation":0,"texture":"#0","tintindex":0},"west":{"uv":[0.0,3.75,0.375,4.125],"rotation":0,"texture":"#0","tintindex":0},"up":{"uv":[4.125,0.375,3.75,0.0],"rotation":0,"texture":"#0","tintindex":0},"down":{"uv":[0.875,3.75,0.5,4.125],"rotation":0,"texture":"#0","tintindex":0}}},{"from":[7.858433,8.043272,4.8655357],"to":[8.144147,8.328986,5.4369645],"rotation":{"angle":0.0,"axis":"y","origin":[5.715575,8.18613,6.0083933]},"faces":{"east":{"uv":[2.0,8.75,2.25,8.875],"rotation":0,"texture":"#0","tintindex":0},"south":{"uv":[9.5,8.0,9.625,8.125],"rotation":0,"texture":"#0","tintindex":0},"north":{"uv":[8.0,9.5,8.125,9.625],"rotation":0,"texture":"#0","tintindex":0},"west":{"uv":[8.75,2.5,9.0,2.625],"rotation":0,"texture":"#0","tintindex":0},"up":{"uv":[8.875,3.0,8.75,2.75],"rotation":0,"texture":"#0","tintindex":0},"down":{"uv":[8.875,3.0,8.75,3.25],"rotation":0,"texture":"#0","tintindex":0}}},{"from":[8.572719,7.900415,6.2941074],"to":[8.572719,8.6147,6.865536],"rotation":{"angle":45.0,"axis":"x","origin":[8.572719,8.328986,6.5798216]},"faces":{"east":{"uv":[3.5,6.5,3.75,6.8125],"rotation":0,"texture":"#0","tintindex":0},"south":{"uv":[0.0,0.0,0.0,0.3125],"rotation":0,"texture":"#0","tintindex":0},"north":{"uv":[0.0,0.0,0.0,0.3125],"rotation":0,"texture":"#0","tintindex":0},"west":{"uv":[3.75,6.5,4.0,6.8125],"rotation":0,"texture":"#0","tintindex":0},"up":{"uv":[0.0,0.25,0.0,0.0],"rotation":0,"texture":"#0","tintindex":0},"down":{"uv":[0.0,0.0,0.0,0.25],"rotation":0,"texture":"#0","tintindex":0}}},{"from":[7.858433,8.043272,4.8655357],"to":[8.144147,8.328986,5.4369645],"rotation":{"angle":0.0,"axis":"y","origin":[5.715575,8.18613,6.0083933]},"faces":{"east":{"uv":[4.25,8.75,4.5,8.875],"rotation":0,"texture":"#0","tintindex":0},"south":{"uv":[9.5,8.25,9.625,8.375],"rotation":0,"texture":"#0","tintindex":0},"north":{"uv":[8.25,9.5,8.375,9.625],"rotation":0,"texture":"#0","tintindex":0},"west":{"uv":[4.5,8.75,4.75,8.875],"rotation":0,"texture":"#0","tintindex":0},"up":{"uv":[4.875,9.0,4.75,8.75],"rotation":0,"texture":"#0","tintindex":0},"down":{"uv":[8.875,4.75,8.75,5.0],"rotation":0,"texture":"#0","tintindex":0}}},{"from":[7.5727186,8.043272,5.4369645],"to":[8.429861,8.900415,6.2941074],"rotation":{"angle":0.0,"axis":"y","origin":[5.715575,8.18613,6.0083933]},"faces":{"east":{"uv":[1.5,3.75,1.875,4.125],"rotation":0,"texture":"#0","tintindex":0},"south":{"uv":[2.0,3.75,2.375,4.125],"rotation":0,"texture":"#0","tintindex":0},"north":{"uv":[1.0,3.75,1.375,4.125],"rotation":0,"texture":"#0","tintindex":0},"west":{"uv":[2.5,3.75,2.875,4.125],"rotation":0,"texture":"#0","tintindex":0},"up":{"uv":[4.375,0.875,4.0,0.5],"rotation":0,"texture":"#0","tintindex":0},"down":{"uv":[3.375,4.0,3.0,4.375],"rotation":0,"texture":"#0","tintindex":0}}},{"from":[7.7155757,8.043272,5.15125],"to":[8.287004,8.6147,5.4369645],"rotation":{"angle":0.0,"axis":"y","origin":[5.715575,8.18613,6.0083933]},"faces":{"east":{"uv":[8.75,5.0,8.875,5.25],"rotation":0,"texture":"#0","tintindex":0},"south":{"uv":[2.25,7.5,2.5,7.75],"rotation":0,"texture":"#0","tintindex":0},"north":{"uv":[7.5,2.0,7.75,2.25],"rotation":0,"texture":"#0","tintindex":0},"west":{"uv":[5.5,8.75,5.625,9.0],"rotation":0,"texture":"#0","tintindex":0},"up":{"uv":[6.0,8.875,5.75,8.75],"rotation":0,"texture":"#0","tintindex":0},"down":{"uv":[9.0,5.75,8.75,5.875],"rotation":0,"texture":"#0","tintindex":0}}},{"from":[7.4298615,8.471844,6.0083933],"to":[8.572719,9.043272,7.1512504],"rotation":{"angle":0.0,"axis":"y","origin":[5.715575,8.18613,6.0083933]},"faces":{"east":{"uv":[5.0,0.75,5.5,1.0],"rotation":0,"texture":"#0","tintindex":0},"south":{"uv":[2.0,5.0,2.5,5.25],"rotation":0,"texture":"#0","tintindex":0},"north":{"uv":[5.0,0.5,5.5,0.75],"rotation":0,"texture":"#0","tintindex":0},"west":{"uv":[2.5,5.0,3.0,5.25],"rotation":0,"texture":"#0","tintindex":0},"up":{"uv":[1.0,0.5,0.5,0.0],"rotation":0,"texture":"#0","tintindex":0},"down":{"uv":[1.0,0.5,0.5,1.0],"rotation":0,"texture":"#0","tintindex":0}}},{"from":[7.5727186,8.328986,6.2941074],"to":[8.429861,8.900415,7.4369645],"rotation":{"angle":0.0,"axis":"y","origin":[5.715575,8.18613,6.0083933]},"faces":{"east":{"uv":[3.0,5.0,3.5,5.25],"rotation":0,"texture":"#0","tintindex":0},"south":{"uv":[5.75,2.0,6.125,2.25],"rotation":0,"texture":"#0","tintindex":0},"north":{"uv":[5.75,1.75,6.125,2.0],"rotation":0,"texture":"#0","tintindex":0},"west":{"uv":[5.0,3.0,5.5,3.25],"rotation":0,"texture":"#0","tintindex":0},"up":{"uv":[0.375,3.5,0.0,3.0],"rotation":0,"texture":"#0","tintindex":0},"down":{"uv":[0.875,3.0,0.5,3.5],"rotation":0,"texture":"#0","tintindex":0}}},{"from":[7.7155757,8.043272,6.2941074],"to":[8.287004,8.6147,7.1512504],"rotation":{"angle":0.0,"axis":"y","origin":[5.715575,8.18613,6.0083933]},"faces":{"east":{"uv":[5.75,2.25,6.125,2.5],"rotation":0,"texture":"#0","tintindex":0},"south":{"uv":[2.5,7.5,2.75,7.75],"rotation":0,"texture":"#0","tintindex":0},"north":{"uv":[7.5,2.25,7.75,2.5],"rotation":0,"texture":"#0","tintindex":0},"west":{"uv":[5.75,2.5,6.125,2.75],"rotation":0,"texture":"#0","tintindex":0},"up":{"uv":[6.0,3.125,5.75,2.75],"rotation":0,"texture":"#0","tintindex":0},"down":{"uv":[6.0,3.25,5.75,3.625],"rotation":0,"texture":"#0","tintindex":0}}},{"from":[7.7155757,9.043272,6.1512504],"to":[8.287004,9.18613,7.1512504],"rotation":{"angle":0.0,"axis":"y","origin":[5.715575,8.18613,6.0083933]},"faces":{"east":{"uv":[3.0,9.25,3.4375,9.3125],"rotation":0,"texture":"#0","tintindex":0},"south":{"uv":[9.5,8.5,9.75,8.5625],"rotation":0,"texture":"#0","tintindex":0},"north":{"uv":[8.5,9.5,8.75,9.5625],"rotation":0,"texture":"#0","tintindex":0},"west":{"uv":[9.25,3.0,9.6875,3.0625],"rotation":0,"texture":"#0","tintindex":0},"up":{"uv":[0.25,5.9375,0.0,5.5],"rotation":0,"texture":"#0","tintindex":0},"down":{"uv":[0.5,5.5,0.25,5.9375],"rotation":0,"texture":"#0","tintindex":0}}},{"from":[7.858433,8.900415,5.5798216],"to":[8.144147,9.043272,6.1512504],"rotation":{"angle":0.0,"axis":"y","origin":[5.715575,8.18613,6.0083933]},"faces":{"east":{"uv":[8.75,9.5,9.0,9.5625],"rotation":0,"texture":"#0","tintindex":0},"south":{"uv":[3.75,9.75,3.875,9.8125],"rotation":0,"texture":"#0","tintindex":0},"north":{"uv":[9.75,3.5,9.875,3.5625],"rotation":0,"texture":"#0","tintindex":0},"west":{"uv":[9.5,8.75,9.75,8.8125],"rotation":0,"texture":"#0","tintindex":0},"up":{"uv":[6.125,9.0,6.0,8.75],"rotation":0,"texture":"#0","tintindex":0},"down":{"uv":[8.875,6.0,8.75,6.25],"rotation":0,"texture":"#0","tintindex":0}}},{"from":[7.4298615,7.900415,6.2941074],"to":[7.4298615,8.6147,6.865536],"rotation":{"angle":45.0,"axis":"x","origin":[7.4298615,8.328986,6.5798216]},"faces":{"east":{"uv":[6.5,3.75,6.75,4.0625],"rotation":0,"texture":"#0","tintindex":0},"south":{"uv":[0.0,0.0,0.0,0.3125],"rotation":0,"texture":"#0","tintindex":0},"north":{"uv":[0.0,0.0,0.0,0.3125],"rotation":0,"texture":"#0","tintindex":0},"west":{"uv":[4.0,6.5,4.25,6.8125],"rotation":0,"texture":"#0","tintindex":0},"up":{"uv":[0.0,0.25,0.0,0.0],"rotation":0,"texture":"#0","tintindex":0},"down":{"uv":[0.0,0.0,0.0,0.25],"rotation":0,"texture":"#0","tintindex":0}}},{"from":[7.2870045,8.360675,5.7645216],"to":[8.715576,8.646389,6.6216645],"rotation":{"angle":-45.0,"axis":"x","origin":[8.858433,9.6147,6.2941074]},"faces":{"east":{"uv":[7.75,5.5,8.125,5.625],"rotation":0,"texture":"#0","tintindex":0},"south":{"uv":[6.5,4.25,7.125,4.375],"rotation":0,"texture":"#0","tintindex":0},"north":{"uv":[4.25,6.5,4.875,6.625],"rotation":0,"texture":"#0","tintindex":0},"west":{"uv":[5.75,7.75,6.125,7.875],"rotation":0,"texture":"#0","tintindex":0},"up":{"uv":[0.625,2.375,0.0,2.0],"rotation":0,"texture":"#0","tintindex":0},"down":{"uv":[2.625,0.0,2.0,0.375],"rotation":0,"texture":"#0","tintindex":0}}},{"from":[7.2870045,8.3534975,6.2349334],"to":[8.715576,8.639212,6.8063617],"rotation":{"angle":0.0,"axis":"y","origin":[5.715575,8.18613,6.0083933]},"faces":{"east":{"uv":[6.25,8.75,6.5,8.875],"rotation":0,"texture":"#0","tintindex":0},"south":{"uv":[6.5,4.75,7.125,4.875],"rotation":0,"texture":"#0","tintindex":0},"north":{"uv":[6.5,4.5,7.125,4.625],"rotation":0,"texture":"#0","tintindex":0},"west":{"uv":[8.75,6.25,9.0,6.375],"rotation":0,"texture":"#0","tintindex":0},"up":{"uv":[0.625,3.75,0.0,3.5],"rotation":0,"texture":"#0","tintindex":0},"down":{"uv":[1.375,3.5,0.75,3.75],"rotation":0,"texture":"#0","tintindex":0}}},{"from":[7.4298615,8.173003,5.8828673],"to":[7.858433,8.458718,6.454296],"rotation":{"angle":-45.0,"axis":"x","origin":[8.572719,8.284172,6.126739]},"faces":{"east":{"uv":[6.5,8.75,6.75,8.875],"rotation":0,"texture":"#0","tintindex":0},"south":{"uv":[9.25,7.5,9.4375,7.625],"rotation":0,"texture":"#0","tintindex":0},"north":{"uv":[7.5,9.25,7.6875,9.375],"rotation":0,"texture":"#0","tintindex":0},"west":{"uv":[6.75,8.75,7.0,8.875],"rotation":0,"texture":"#0","tintindex":0},"up":{"uv":[7.9375,6.0,7.75,5.75],"rotation":0,"texture":"#0","tintindex":0},"down":{"uv":[7.9375,6.0,7.75,6.25],"rotation":0,"texture":"#0","tintindex":0}}},{"from":[8.144147,8.173003,5.8828673],"to":[8.572719,8.458718,6.454296],"rotation":{"angle":-45.0,"axis":"x","origin":[7.4298615,8.284172,6.126739]},"faces":{"east":{"uv":[8.75,6.75,9.0,6.875],"rotation":0,"texture":"#0","tintindex":0},"south":{"uv":[9.25,7.75,9.4375,7.875],"rotation":0,"texture":"#0","tintindex":0},"north":{"uv":[7.75,9.25,7.9375,9.375],"rotation":0,"texture":"#0","tintindex":0},"west":{"uv":[8.75,7.0,9.0,7.125],"rotation":0,"texture":"#0","tintindex":0},"up":{"uv":[6.4375,8.0,6.25,7.75],"rotation":0,"texture":"#0","tintindex":0},"down":{"uv":[7.9375,6.25,7.75,6.5],"rotation":0,"texture":"#0","tintindex":0}}},{"from":[7.7155757,7.757558,6.1512504],"to":[8.287004,8.043272,7.1512504],"rotation":{"angle":0.0,"axis":"y","origin":[5.715575,8.18613,6.0083933]},"faces":{"east":{"uv":[7.75,0.0,8.1875,0.125],"rotation":0,"texture":"#0","tintindex":0},"south":{"uv":[8.75,7.5,9.0,7.625],"rotation":0,"texture":"#0","tintindex":0},"north":{"uv":[8.75,7.25,9.0,7.375],"rotation":0,"texture":"#0","tintindex":0},"west":{"uv":[7.75,0.25,8.1875,0.375],"rotation":0,"texture":"#0","tintindex":0},"up":{"uv":[0.75,5.9375,0.5,5.5],"rotation":0,"texture":"#0","tintindex":0},"down":{"uv":[5.75,0.5,5.5,0.9375],"rotation":0,"texture":"#0","tintindex":0}}},{"from":[7.858433,7.900415,5.15125],"to":[8.144147,8.043272,6.1512504],"rotation":{"angle":0.0,"axis":"y","origin":[5.715575,8.18613,6.0083933]},"faces":{"east":{"uv":[9.25,3.25,9.6875,3.3125],"rotation":0,"texture":"#0","tintindex":0},"south":{"uv":[4.0,9.75,4.125,9.8125],"rotation":0,"texture":"#0","tintindex":0},"north":{"uv":[9.75,3.75,9.875,3.8125],"rotation":0,"texture":"#0","tintindex":0},"west":{"uv":[3.5,9.25,3.9375,9.3125],"rotation":0,"texture":"#0","tintindex":0},"up":{"uv":[0.625,8.1875,0.5,7.75],"rotation":0,"texture":"#0","tintindex":0},"down":{"uv":[7.875,0.5,7.75,0.9375],"rotation":0,"texture":"#0","tintindex":0}}},{"from":[8.572719,7.900415,6.2941074],"to":[8.572719,8.6147,6.865536],"rotation":{"angle":45.0,"axis":"x","origin":[8.572719,8.328986,6.5798216]},"faces":{"east":{"uv":[5.0,6.5,5.25,6.8125],"rotation":0,"texture":"#0","tintindex":0},"south":{"uv":[0.0,0.0,0.0,0.3125],"rotation":0,"texture":"#0","tintindex":0},"north":{"uv":[0.0,0.0,0.0,0.3125],"rotation":0,"texture":"#0","tintindex":0},"west":{"uv":[5.25,6.5,5.5,6.8125],"rotation":0,"texture":"#0","tintindex":0},"up":{"uv":[0.0,0.25,0.0,0.0],"rotation":0,"texture":"#0","tintindex":0},"down":{"uv":[0.0,0.0,0.0,0.25],"rotation":0,"texture":"#0","tintindex":0}}},{"from":[7.858433,8.043272,4.8655357],"to":[8.144147,8.328986,5.4369645],"rotation":{"angle":0.0,"axis":"y","origin":[5.715575,8.18613,6.0083933]},"faces":{"east":{"uv":[7.75,8.75,8.0,8.875],"rotation":0,"texture":"#0","tintindex":0},"south":{"uv":[9.5,9.0,9.625,9.125],"rotation":0,"texture":"#0","tintindex":0},"north":{"uv":[9.0,9.5,9.125,9.625],"rotation":0,"texture":"#0","tintindex":0},"west":{"uv":[8.75,7.75,9.0,7.875],"rotation":0,"texture":"#0","tintindex":0},"up":{"uv":[8.125,9.0,8.0,8.75],"rotation":0,"texture":"#0","tintindex":0},"down":{"uv":[8.875,8.0,8.75,8.25],"rotation":0,"texture":"#0","tintindex":0}}},{"from":[7.5727186,8.043272,5.4369645],"to":[8.429861,8.900415,6.2941074],"rotation":{"angle":0.0,"axis":"y","origin":[5.715575,8.18613,6.0083933]},"faces":{"east":{"uv":[3.5,4.0,3.875,4.375],"rotation":0,"texture":"#0","tintindex":0},"south":{"uv":[4.0,3.5,4.375,3.875],"rotation":0,"texture":"#0","tintindex":0},"north":{"uv":[4.0,3.0,4.375,3.375],"rotation":0,"texture":"#0","tintindex":0},"west":{"uv":[4.0,4.0,4.375,4.375],"rotation":0,"texture":"#0","tintindex":0},"up":{"uv":[0.375,4.625,0.0,4.25],"rotation":0,"texture":"#0","tintindex":0},"down":{"uv":[4.625,0.0,4.25,0.375],"rotation":0,"texture":"#0","tintindex":0}}},{"from":[7.7155757,8.043272,5.15125],"to":[8.287004,8.6147,5.4369645],"rotation":{"angle":0.0,"axis":"y","origin":[5.715575,8.18613,6.0083933]},"faces":{"east":{"uv":[8.25,8.75,8.375,9.0],"rotation":0,"texture":"#0","tintindex":0},"south":{"uv":[2.75,7.5,3.0,7.75],"rotation":0,"texture":"#0","tintindex":0},"north":{"uv":[7.5,2.5,7.75,2.75],"rotation":0,"texture":"#0","tintindex":0},"west":{"uv":[8.75,8.25,8.875,8.5],"rotation":0,"texture":"#0","tintindex":0},"up":{"uv":[8.75,8.875,8.5,8.75],"rotation":0,"texture":"#0","tintindex":0},"down":{"uv":[9.0,8.5,8.75,8.625],"rotation":0,"texture":"#0","tintindex":0}}},{"from":[7.4298615,8.471844,6.0083933],"to":[8.572719,9.043272,7.1512504],"rotation":{"angle":0.0,"axis":"y","origin":[5.715575,8.18613,6.0083933]},"faces":{"east":{"uv":[3.5,5.0,4.0,5.25],"rotation":0,"texture":"#0","tintindex":0},"south":{"uv":[5.0,3.5,5.5,3.75],"rotation":0,"texture":"#0","tintindex":0},"north":{"uv":[5.0,3.25,5.5,3.5],"rotation":0,"texture":"#0","tintindex":0},"west":{"uv":[5.0,3.75,5.5,4.0],"rotation":0,"texture":"#0","tintindex":0},"up":{"uv":[0.5,1.5,0.0,1.0],"rotation":0,"texture":"#0","tintindex":0},"down":{"uv":[1.5,0.0,1.0,0.5],"rotation":0,"texture":"#0","tintindex":0}}},{"from":[7.5727186,8.328986,6.2941074],"to":[8.429861,8.900415,7.4369645],"rotation":{"angle":0.0,"axis":"y","origin":[5.715575,8.18613,6.0083933]},"faces":{"east":{"uv":[4.0,5.0,4.5,5.25],"rotation":0,"texture":"#0","tintindex":0},"south":{"uv":[5.75,4.0,6.125,4.25],"rotation":0,"texture":"#0","tintindex":0},"north":{"uv":[5.75,3.75,6.125,4.0],"rotation":0,"texture":"#0","tintindex":0},"west":{"uv":[5.0,4.0,5.5,4.25],"rotation":0,"texture":"#0","tintindex":0},"up":{"uv":[1.375,3.5,1.0,3.0],"rotation":0,"texture":"#0","tintindex":0},"down":{"uv":[3.375,1.0,3.0,1.5],"rotation":0,"texture":"#0","tintindex":0}}},{"from":[7.7155757,8.043272,6.2941074],"to":[8.287004,8.6147,7.1512504],"rotation":{"angle":0.0,"axis":"y","origin":[5.715575,8.18613,6.0083933]},"faces":{"east":{"uv":[5.75,4.25,6.125,4.5],"rotation":0,"texture":"#0","tintindex":0},"south":{"uv":[3.25,7.5,3.5,7.75],"rotation":0,"texture":"#0","tintindex":0},"north":{"uv":[3.0,7.5,3.25,7.75],"rotation":0,"texture":"#0","tintindex":0},"west":{"uv":[4.5,5.75,4.875,6.0],"rotation":0,"texture":"#0","tintindex":0},"up":{"uv":[6.0,4.875,5.75,4.5],"rotation":0,"texture":"#0","tintindex":0},"down":{"uv":[5.25,5.75,5.0,6.125],"rotation":0,"texture":"#0","tintindex":0}}},{"from":[7.7155757,9.043272,6.1512504],"to":[8.287004,9.18613,7.1512504],"rotation":{"angle":0.0,"axis":"y","origin":[5.715575,8.18613,6.0083933]},"faces":{"east":{"uv":[9.25,3.5,9.6875,3.5625],"rotation":0,"texture":"#0","tintindex":0},"south":{"uv":[9.5,9.25,9.75,9.3125],"rotation":0,"texture":"#0","tintindex":0},"north":{"uv":[9.25,9.5,9.5,9.5625],"rotation":0,"texture":"#0","tintindex":0},"west":{"uv":[9.25,3.75,9.6875,3.8125],"rotation":0,"texture":"#0","tintindex":0},"up":{"uv":[1.0,5.9375,0.75,5.5],"rotation":0,"texture":"#0","tintindex":0},"down":{"uv":[1.25,5.5,1.0,5.9375],"rotation":0,"texture":"#0","tintindex":0}}},{"from":[7.858433,8.900415,5.5798216],"to":[8.144147,9.043272,6.1512504],"rotation":{"angle":0.0,"axis":"y","origin":[5.715575,8.18613,6.0083933]},"faces":{"east":{"uv":[9.5,9.5,9.75,9.5625],"rotation":0,"texture":"#0","tintindex":0},"south":{"uv":[4.25,9.75,4.375,9.8125],"rotation":0,"texture":"#0","tintindex":0},"north":{"uv":[9.75,4.0,9.875,4.0625],"rotation":0,"texture":"#0","tintindex":0},"west":{"uv":[0.0,9.75,0.25,9.8125],"rotation":0,"texture":"#0","tintindex":0},"up":{"uv":[8.875,9.0,8.75,8.75],"rotation":0,"texture":"#0","tintindex":0},"down":{"uv":[0.125,9.0,0.0,9.25],"rotation":0,"texture":"#0","tintindex":0}}},{"from":[7.4298615,7.900415,6.2941074],"to":[7.4298615,8.6147,6.865536],"rotation":{"angle":45.0,"axis":"x","origin":[7.4298615,8.328986,6.5798216]},"faces":{"east":{"uv":[5.5,6.5,5.75,6.8125],"rotation":0,"texture":"#0","tintindex":0},"south":{"uv":[0.0,0.0,0.0,0.3125],"rotation":0,"texture":"#0","tintindex":0},"north":{"uv":[0.0,0.0,0.0,0.3125],"rotation":0,"texture":"#0","tintindex":0},"west":{"uv":[6.5,5.75,6.75,6.0625],"rotation":0,"texture":"#0","tintindex":0},"up":{"uv":[0.0,0.25,0.0,0.0],"rotation":0,"texture":"#0","tintindex":0},"down":{"uv":[0.0,0.0,0.0,0.25],"rotation":0,"texture":"#0","tintindex":0}}},{"from":[7.2870045,8.360675,5.7645216],"to":[8.715576,8.646389,6.6216645],"rotation":{"angle":-45.0,"axis":"x","origin":[8.858433,9.6147,6.2941074]},"faces":{"east":{"uv":[6.5,7.75,6.875,7.875],"rotation":0,"texture":"#0","tintindex":0},"south":{"uv":[6.25,6.5,6.875,6.625],"rotation":0,"texture":"#0","tintindex":0},"north":{"uv":[6.5,5.0,7.125,5.125],"rotation":0,"texture":"#0","tintindex":0},"west":{"uv":[7.75,6.5,8.125,6.625],"rotation":0,"texture":"#0","tintindex":0},"up":{"uv":[2.625,0.875,2.0,0.5],"rotation":0,"texture":"#0","tintindex":0},"down":{"uv":[1.375,2.0,0.75,2.375],"rotation":0,"texture":"#0","tintindex":0}}},{"from":[7.2870045,8.3534975,6.2349334],"to":[8.715576,8.639212,6.8063617],"rotation":{"angle":0.0,"axis":"y","origin":[5.715575,8.18613,6.0083933]},"faces":{"east":{"uv":[9.0,0.0,9.25,0.125],"rotation":0,"texture":"#0","tintindex":0},"south":{"uv":[1.75,6.75,2.375,6.875],"rotation":0,"texture":"#0","tintindex":0},"north":{"uv":[6.5,6.25,7.125,6.375],"rotation":0,"texture":"#0","tintindex":0},"west":{"uv":[9.0,0.25,9.25,0.375],"rotation":0,"texture":"#0","tintindex":0},"up":{"uv":[4.125,1.25,3.5,1.0],"rotation":0,"texture":"#0","tintindex":0},"down":{"uv":[4.125,1.25,3.5,1.5],"rotation":0,"texture":"#0","tintindex":0}}},{"from":[7.4298615,8.173003,5.8828673],"to":[7.858433,8.458718,6.454296],"rotation":{"angle":-45.0,"axis":"x","origin":[8.572719,8.284172,6.126739]},"faces":{"east":{"uv":[9.0,0.5,9.25,0.625],"rotation":0,"texture":"#0","tintindex":0},"south":{"uv":[9.25,8.0,9.4375,8.125],"rotation":0,"texture":"#0","tintindex":0},"north":{"uv":[8.0,9.25,8.1875,9.375],"rotation":0,"texture":"#0","tintindex":0},"west":{"uv":[9.0,0.75,9.25,0.875],"rotation":0,"texture":"#0","tintindex":0},"up":{"uv":[7.9375,7.0,7.75,6.75],"rotation":0,"texture":"#0","tintindex":0},"down":{"uv":[7.1875,7.75,7.0,8.0],"rotation":0,"texture":"#0","tintindex":0}}},{"from":[8.144147,8.173003,5.8828673],"to":[8.572719,8.458718,6.454296],"rotation":{"angle":-45.0,"axis":"x","origin":[7.4298615,8.284172,6.126739]},"faces":{"east":{"uv":[1.0,9.0,1.25,9.125],"rotation":0,"texture":"#0","tintindex":0},"south":{"uv":[9.25,8.25,9.4375,8.375],"rotation":0,"texture":"#0","tintindex":0},"north":{"uv":[8.25,9.25,8.4375,9.375],"rotation":0,"texture":"#0","tintindex":0},"west":{"uv":[9.0,1.0,9.25,1.125],"rotation":0,"texture":"#0","tintindex":0},"up":{"uv":[7.9375,7.25,7.75,7.0],"rotation":0,"texture":"#0","tintindex":0},"down":{"uv":[7.9375,7.25,7.75,7.5],"rotation":0,"texture":"#0","tintindex":0}}},{"from":[7.7155757,7.757558,6.1512504],"to":[8.287004,8.043272,7.1512504],"rotation":{"angle":0.0,"axis":"y","origin":[5.715575,8.18613,6.0083933]},"faces":{"east":{"uv":[0.75,7.75,1.1875,7.875],"rotation":0,"texture":"#0","tintindex":0},"south":{"uv":[1.5,9.0,1.75,9.125],"rotation":0,"texture":"#0","tintindex":0},"north":{"uv":[1.25,9.0,1.5,9.125],"rotation":0,"texture":"#0","tintindex":0},"west":{"uv":[7.75,1.0,8.1875,1.125],"rotation":0,"texture":"#0","tintindex":0},"up":{"uv":[1.5,5.9375,1.25,5.5],"rotation":0,"texture":"#0","tintindex":0},"down":{"uv":[1.75,5.5,1.5,5.9375],"rotation":0,"texture":"#0","tintindex":0}}},{"from":[7.858433,7.900415,5.15125],"to":[8.144147,8.043272,6.1512504],"rotation":{"angle":0.0,"axis":"y","origin":[5.715575,8.18613,6.0083933]},"faces":{"east":{"uv":[4.0,9.25,4.4375,9.3125],"rotation":0,"texture":"#0","tintindex":0},"south":{"uv":[4.5,9.75,4.625,9.8125],"rotation":0,"texture":"#0","tintindex":0},"north":{"uv":[9.75,4.25,9.875,4.3125],"rotation":0,"texture":"#0","tintindex":0},"west":{"uv":[9.25,4.0,9.6875,4.0625],"rotation":0,"texture":"#0","tintindex":0},"up":{"uv":[7.875,1.6875,7.75,1.25],"rotation":0,"texture":"#0","tintindex":0},"down":{"uv":[1.625,7.75,1.5,8.1875],"rotation":0,"texture":"#0","tintindex":0}}},{"from":[8.572719,7.900415,6.2941074],"to":[8.572719,8.6147,6.865536],"rotation":{"angle":45.0,"axis":"x","origin":[8.572719,8.328986,6.5798216]},"faces":{"east":{"uv":[6.75,3.25,7.0,3.5625],"rotation":0,"texture":"#0","tintindex":0},"south":{"uv":[0.0,0.0,0.0,0.3125],"rotation":0,"texture":"#0","tintindex":0},"north":{"uv":[0.0,0.0,0.0,0.3125],"rotation":0,"texture":"#0","tintindex":0},"west":{"uv":[6.75,3.75,7.0,4.0625],"rotation":0,"texture":"#0","tintindex":0},"up":{"uv":[0.0,0.25,0.0,0.0],"rotation":0,"texture":"#0","tintindex":0},"down":{"uv":[0.0,0.0,0.0,0.25],"rotation":0,"texture":"#0","tintindex":0}}},{"from":[7.858433,8.043272,4.8655357],"to":[8.144147,8.328986,5.4369645],"rotation":{"angle":0.0,"axis":"y","origin":[5.715575,8.18613,6.0083933]},"faces":{"east":{"uv":[1.75,9.0,2.0,9.125],"rotation":0,"texture":"#0","tintindex":0},"south":{"uv":[0.25,9.75,0.375,9.875],"rotation":0,"texture":"#0","tintindex":0},"north":{"uv":[9.75,0.0,9.875,0.125],"rotation":0,"texture":"#0","tintindex":0},"west":{"uv":[9.0,1.75,9.25,1.875],"rotation":0,"texture":"#0","tintindex":0},"up":{"uv":[2.125,9.25,2.0,9.0],"rotation":0,"texture":"#0","tintindex":0},"down":{"uv":[9.125,2.0,9.0,2.25],"rotation":0,"texture":"#0","tintindex":0}}},{"from":[7.5727186,8.043272,5.4369645],"to":[8.429861,8.900415,6.2941074],"rotation":{"angle":0.0,"axis":"y","origin":[5.715575,8.18613,6.0083933]},"faces":{"east":{"uv":[1.0,4.25,1.375,4.625],"rotation":0,"texture":"#0","tintindex":0},"south":{"uv":[4.25,1.0,4.625,1.375],"rotation":0,"texture":"#0","tintindex":0},"north":{"uv":[0.5,4.25,0.875,4.625],"rotation":0,"texture":"#0","tintindex":0},"west":{"uv":[1.5,4.25,1.875,4.625],"rotation":0,"texture":"#0","tintindex":0},"up":{"uv":[4.625,1.875,4.25,1.5],"rotation":0,"texture":"#0","tintindex":0},"down":{"uv":[2.375,4.25,2.0,4.625],"rotation":0,"texture":"#0","tintindex":0}}},{"from":[7.7155757,8.043272,5.15125],"to":[8.287004,8.6147,5.4369645],"rotation":{"angle":0.0,"axis":"y","origin":[5.715575,8.18613,6.0083933]},"faces":{"east":{"uv":[2.25,9.0,2.375,9.25],"rotation":0,"texture":"#0","tintindex":0},"south":{"uv":[7.5,3.75,7.75,4.0],"rotation":0,"texture":"#0","tintindex":0},"north":{"uv":[3.75,7.5,4.0,7.75],"rotation":0,"texture":"#0","tintindex":0},"west":{"uv":[2.5,9.0,2.625,9.25],"rotation":0,"texture":"#0","tintindex":0},"up":{"uv":[9.25,2.625,9.0,2.5],"rotation":0,"texture":"#0","tintindex":0},"down":{"uv":[3.0,9.0,2.75,9.125],"rotation":0,"texture":"#0","tintindex":0}}},{"from":[7.4298615,8.471844,6.0083933],"to":[8.572719,9.043272,7.1512504],"rotation":{"angle":0.0,"axis":"y","origin":[5.715575,8.18613,6.0083933]},"faces":{"east":{"uv":[4.5,5.0,5.0,5.25],"rotation":0,"texture":"#0","tintindex":0},"south":{"uv":[5.0,4.5,5.5,4.75],"rotation":0,"texture":"#0","tintindex":0},"north":{"uv":[5.0,4.25,5.5,4.5],"rotation":0,"texture":"#0","tintindex":0},"west":{"uv":[5.0,4.75,5.5,5.0],"rotation":0,"texture":"#0","tintindex":0},"up":{"uv":[1.0,1.5,0.5,1.0],"rotation":0,"texture":"#0","tintindex":0},"down":{"uv":[1.5,0.5,1.0,1.0],"rotation":0,"texture":"#0","tintindex":0}}},{"from":[7.5727186,8.328986,6.2941074],"to":[8.429861,8.900415,7.4369645],"rotation":{"angle":0.0,"axis":"y","origin":[5.715575,8.18613,6.0083933]},"faces":{"east":{"uv":[5.0,5.0,5.5,5.25],"rotation":0,"texture":"#0","tintindex":0},"south":{"uv":[5.25,5.75,5.625,6.0],"rotation":0,"texture":"#0","tintindex":0},"north":{"uv":[5.75,5.0,6.125,5.25],"rotation":0,"texture":"#0","tintindex":0},"west":{"uv":[0.0,5.25,0.5,5.5],"rotation":0,"texture":"#0","tintindex":0},"up":{"uv":[1.875,3.5,1.5,3.0],"rotation":0,"texture":"#0","tintindex":0},"down":{"uv":[3.375,1.5,3.0,2.0],"rotation":0,"texture":"#0","tintindex":0}}},{"from":[7.7155757,8.043272,6.2941074],"to":[8.287004,8.6147,7.1512504],"rotation":{"angle":0.0,"axis":"y","origin":[5.715575,8.18613,6.0083933]},"faces":{"east":{"uv":[5.75,5.25,6.125,5.5],"rotation":0,"texture":"#0","tintindex":0},"south":{"uv":[7.5,4.0,7.75,4.25],"rotation":0,"texture":"#0","tintindex":0},"north":{"uv":[4.0,7.5,4.25,7.75],"rotation":0,"texture":"#0","tintindex":0},"west":{"uv":[5.75,5.75,6.125,6.0],"rotation":0,"texture":"#0","tintindex":0},"up":{"uv":[0.25,6.375,0.0,6.0],"rotation":0,"texture":"#0","tintindex":0},"down":{"uv":[0.5,6.0,0.25,6.375],"rotation":0,"texture":"#0","tintindex":0}}},{"from":[7.7155757,9.043272,6.1512504],"to":[8.287004,9.18613,7.1512504],"rotation":{"angle":0.0,"axis":"y","origin":[5.715575,8.18613,6.0083933]},"faces":{"east":{"uv":[9.25,4.25,9.6875,4.3125],"rotation":0,"texture":"#0","tintindex":0},"south":{"uv":[0.5,9.75,0.75,9.8125],"rotation":0,"texture":"#0","tintindex":0},"north":{"uv":[9.75,0.25,10.0,0.3125],"rotation":0,"texture":"#0","tintindex":0},"west":{"uv":[4.5,9.25,4.9375,9.3125],"rotation":0,"texture":"#0","tintindex":0},"up":{"uv":[2.0,5.9375,1.75,5.5],"rotation":0,"texture":"#0","tintindex":0},"down":{"uv":[2.25,5.5,2.0,5.9375],"rotation":0,"texture":"#0","tintindex":0}}},{"from":[7.858433,8.900415,5.5798216],"to":[8.144147,9.043272,6.1512504],"rotation":{"angle":0.0,"axis":"y","origin":[5.715575,8.18613,6.0083933]},"faces":{"east":{"uv":[9.75,0.5,10.0,0.5625],"rotation":0,"texture":"#0","tintindex":0},"south":{"uv":[4.75,9.75,4.875,9.8125],"rotation":0,"texture":"#0","tintindex":0},"north":{"uv":[9.75,4.5,9.875,4.5625],"rotation":0,"texture":"#0","tintindex":0},"west":{"uv":[0.75,9.75,1.0,9.8125],"rotation":0,"texture":"#0","tintindex":0},"up":{"uv":[9.125,3.0,9.0,2.75],"rotation":0,"texture":"#0","tintindex":0},"down":{"uv":[9.125,3.0,9.0,3.25],"rotation":0,"texture":"#0","tintindex":0}}},{"from":[7.4298615,7.900415,6.2941074],"to":[7.4298615,8.6147,6.865536],"rotation":{"angle":45.0,"axis":"x","origin":[7.4298615,8.328986,6.5798216]},"faces":{"east":{"uv":[4.25,6.75,4.5,7.0625],"rotation":0,"texture":"#0","tintindex":0},"south":{"uv":[0.0,0.0,0.0,0.3125],"rotation":0,"texture":"#0","tintindex":0},"north":{"uv":[0.0,0.0,0.0,0.3125],"rotation":0,"texture":"#0","tintindex":0},"west":{"uv":[4.5,6.75,4.75,7.0625],"rotation":0,"texture":"#0","tintindex":0},"up":{"uv":[0.0,0.25,0.0,0.0],"rotation":0,"texture":"#0","tintindex":0},"down":{"uv":[0.0,0.0,0.0,0.25],"rotation":0,"texture":"#0","tintindex":0}}},{"from":[7.2870045,8.360675,5.7645216],"to":[8.715576,8.646389,6.6216645],"rotation":{"angle":-45.0,"axis":"x","origin":[8.858433,9.6147,6.2941074]},"faces":{"east":{"uv":[7.5,7.75,7.875,7.875],"rotation":0,"texture":"#0","tintindex":0},"south":{"uv":[6.75,5.75,7.375,5.875],"rotation":0,"texture":"#0","tintindex":0},"north":{"uv":[6.75,5.5,7.375,5.625],"rotation":0,"texture":"#0","tintindex":0},"west":{"uv":[0.0,8.0,0.375,8.125],"rotation":0,"texture":"#0","tintindex":0},"up":{"uv":[2.125,2.375,1.5,2.0],"rotation":0,"texture":"#0","tintindex":0},"down":{"uv":[2.875,1.0,2.25,1.375],"rotation":0,"texture":"#0","tintindex":0}}},{"from":[7.2870045,8.3534975,6.2349334],"to":[8.715576,8.639212,6.8063617],"rotation":{"angle":0.0,"axis":"y","origin":[5.715575,8.18613,6.0083933]},"faces":{"east":{"uv":[9.0,3.25,9.25,3.375],"rotation":0,"texture":"#0","tintindex":0},"south":{"uv":[6.75,6.0,7.375,6.125],"rotation":0,"texture":"#0","tintindex":0},"north":{"uv":[6.0,6.75,6.625,6.875],"rotation":0,"texture":"#0","tintindex":0},"west":{"uv":[3.75,9.0,4.0,9.125],"rotation":0,"texture":"#0","tintindex":0},"up":{"uv":[2.125,3.75,1.5,3.5],"rotation":0,"texture":"#0","tintindex":0},"down":{"uv":[4.125,1.5,3.5,1.75],"rotation":0,"texture":"#0","tintindex":0}}},{"from":[7.4298615,8.173003,5.8828673],"to":[7.858433,8.458718,6.454296],"rotation":{"angle":-45.0,"axis":"x","origin":[8.572719,8.284172,6.126739]},"faces":{"east":{"uv":[4.0,9.0,4.25,9.125],"rotation":0,"texture":"#0","tintindex":0},"south":{"uv":[9.25,8.5,9.4375,8.625],"rotation":0,"texture":"#0","tintindex":0},"north":{"uv":[8.5,9.25,8.6875,9.375],"rotation":0,"texture":"#0","tintindex":0},"west":{"uv":[9.0,4.0,9.25,4.125],"rotation":0,"texture":"#0","tintindex":0},"up":{"uv":[8.1875,0.75,8.0,0.5],"rotation":0,"texture":"#0","tintindex":0},"down":{"uv":[0.9375,8.0,0.75,8.25],"rotation":0,"texture":"#0","tintindex":0}}},{"from":[8.144147,8.173003,5.8828673],"to":[8.572719,8.458718,6.454296],"rotation":{"angle":-45.0,"axis":"x","origin":[7.4298615,8.284172,6.126739]},"faces":{"east":{"uv":[4.25,9.0,4.5,9.125],"rotation":0,"texture":"#0","tintindex":0},"south":{"uv":[9.25,8.75,9.4375,8.875],"rotation":0,"texture":"#0","tintindex":0},"north":{"uv":[8.75,9.25,8.9375,9.375],"rotation":0,"texture":"#0","tintindex":0},"west":{"uv":[9.0,4.25,9.25,4.375],"rotation":0,"texture":"#0","tintindex":0},"up":{"uv":[8.1875,1.0,8.0,0.75],"rotation":0,"texture":"#0","tintindex":0},"down":{"uv":[1.1875,8.0,1.0,8.25],"rotation":0,"texture":"#0","tintindex":0}}},{"from":[7.7155757,7.757558,6.1512504],"to":[8.287004,8.043272,7.1512504],"rotation":{"angle":0.0,"axis":"y","origin":[5.715575,8.18613,6.0083933]},"faces":{"east":{"uv":[1.75,7.75,2.1875,7.875],"rotation":0,"texture":"#0","tintindex":0},"south":{"uv":[9.0,4.5,9.25,4.625],"rotation":0,"texture":"#0","tintindex":0},"north":{"uv":[4.5,9.0,4.75,9.125],"rotation":0,"texture":"#0","tintindex":0},"west":{"uv":[7.75,1.75,8.1875,1.875],"rotation":0,"texture":"#0","tintindex":0},"up":{"uv":[2.5,5.9375,2.25,5.5],"rotation":0,"texture":"#0","tintindex":0},"down":{"uv":[2.75,5.5,2.5,5.9375],"rotation":0,"texture":"#0","tintindex":0}}},{"from":[7.858433,7.900415,5.15125],"to":[8.144147,8.043272,6.1512504],"rotation":{"angle":0.0,"axis":"y","origin":[5.715575,8.18613,6.0083933]},"faces":{"east":{"uv":[9.25,4.5,9.6875,4.5625],"rotation":0,"texture":"#0","tintindex":0},"south":{"uv":[5.0,9.75,5.125,9.8125],"rotation":0,"texture":"#0","tintindex":0},"north":{"uv":[9.75,4.75,9.875,4.8125],"rotation":0,"texture":"#0","tintindex":0},"west":{"uv":[9.25,4.75,9.6875,4.8125],"rotation":0,"texture":"#0","tintindex":0},"up":{"uv":[7.875,2.4375,7.75,2.0],"rotation":0,"texture":"#0","tintindex":0},"down":{"uv":[2.375,7.75,2.25,8.1875],"rotation":0,"texture":"#0","tintindex":0}}},{"from":[8.572719,7.900415,6.2941074],"to":[8.572719,8.6147,6.865536],"rotation":{"angle":45.0,"axis":"x","origin":[8.572719,8.328986,6.5798216]},"faces":{"east":{"uv":[4.75,6.75,5.0,7.0625],"rotation":0,"texture":"#0","tintindex":0},"south":{"uv":[0.0,0.0,0.0,0.3125],"rotation":0,"texture":"#0","tintindex":0},"north":{"uv":[0.0,0.0,0.0,0.3125],"rotation":0,"texture":"#0","tintindex":0},"west":{"uv":[6.75,6.75,7.0,7.0625],"rotation":0,"texture":"#0","tintindex":0},"up":{"uv":[0.0,0.25,0.0,0.0],"rotation":0,"texture":"#0","tintindex":0},"down":{"uv":[0.0,0.0,0.0,0.25],"rotation":0,"texture":"#0","tintindex":0}}},{"from":[7.858433,8.043272,4.8655357],"to":[8.144147,8.328986,5.4369645],"rotation":{"angle":0.0,"axis":"y","origin":[5.715575,8.18613,6.0083933]},"faces":{"east":{"uv":[4.75,9.0,5.0,9.125],"rotation":0,"texture":"#0","tintindex":0},"south":{"uv":[1.0,9.75,1.125,9.875],"rotation":0,"texture":"#0","tintindex":0},"north":{"uv":[9.75,0.75,9.875,0.875],"rotation":0,"texture":"#0","tintindex":0},"west":{"uv":[9.0,4.75,9.25,4.875],"rotation":0,"texture":"#0","tintindex":0},"up":{"uv":[5.125,9.25,5.0,9.0],"rotation":0,"texture":"#0","tintindex":0},"down":{"uv":[9.125,5.0,9.0,5.25],"rotation":0,"texture":"#0","tintindex":0}}},{"from":[7.5727186,8.043272,5.4369645],"to":[8.429861,8.900415,6.2941074],"rotation":{"angle":0.0,"axis":"y","origin":[5.715575,8.18613,6.0083933]},"faces":{"east":{"uv":[2.5,4.25,2.875,4.625],"rotation":0,"texture":"#0","tintindex":0},"south":{"uv":[4.25,2.5,4.625,2.875],"rotation":0,"texture":"#0","tintindex":0},"north":{"uv":[4.25,2.0,4.625,2.375],"rotation":0,"texture":"#0","tintindex":0},"west":{"uv":[4.5,0.5,4.875,0.875],"rotation":0,"texture":"#0","tintindex":0},"up":{"uv":[3.375,4.875,3.0,4.5],"rotation":0,"texture":"#0","tintindex":0},"down":{"uv":[4.875,3.0,4.5,3.375],"rotation":0,"texture":"#0","tintindex":0}}},{"from":[7.7155757,8.043272,5.15125],"to":[8.287004,8.6147,5.4369645],"rotation":{"angle":0.0,"axis":"y","origin":[5.715575,8.18613,6.0083933]},"faces":{"east":{"uv":[5.25,9.0,5.375,9.25],"rotation":0,"texture":"#0","tintindex":0},"south":{"uv":[4.5,7.5,4.75,7.75],"rotation":0,"texture":"#0","tintindex":0},"north":{"uv":[4.25,7.5,4.5,7.75],"rotation":0,"texture":"#0","tintindex":0},"west":{"uv":[9.0,5.25,9.125,5.5],"rotation":0,"texture":"#0","tintindex":0},"up":{"uv":[5.75,9.125,5.5,9.0],"rotation":0,"texture":"#0","tintindex":0},"down":{"uv":[9.25,5.5,9.0,5.625],"rotation":0,"texture":"#0","tintindex":0}}},{"from":[7.4298615,8.471844,6.0083933],"to":[8.572719,9.043272,7.1512504],"rotation":{"angle":0.0,"axis":"y","origin":[5.715575,8.18613,6.0083933]},"faces":{"east":{"uv":[5.25,0.25,5.75,0.5],"rotation":0,"texture":"#0","tintindex":0},"south":{"uv":[0.5,5.25,1.0,5.5],"rotation":0,"texture":"#0","tintindex":0},"north":{"uv":[5.25,0.0,5.75,0.25],"rotation":0,"texture":"#0","tintindex":0},"west":{"uv":[1.0,5.25,1.5,5.5],"rotation":0,"texture":"#0","tintindex":0},"up":{"uv":[1.5,1.5,1.0,1.0],"rotation":0,"texture":"#0","tintindex":0},"down":{"uv":[0.5,1.5,0.0,2.0],"rotation":0,"texture":"#0","tintindex":0}}},{"from":[7.5727186,8.328986,6.2941074],"to":[8.429861,8.900415,7.4369645],"rotation":{"angle":0.0,"axis":"y","origin":[5.715575,8.18613,6.0083933]},"faces":{"east":{"uv":[5.25,1.0,5.75,1.25],"rotation":0,"texture":"#0","tintindex":0},"south":{"uv":[0.5,6.0,0.875,6.25],"rotation":0,"texture":"#0","tintindex":0},"north":{"uv":[6.0,0.25,6.375,0.5],"rotation":0,"texture":"#0","tintindex":0},"west":{"uv":[5.25,1.25,5.75,1.5],"rotation":0,"texture":"#0","tintindex":0},"up":{"uv":[2.375,3.5,2.0,3.0],"rotation":0,"texture":"#0","tintindex":0},"down":{"uv":[3.375,2.0,3.0,2.5],"rotation":0,"texture":"#0","tintindex":0}}},{"from":[7.7155757,8.043272,6.2941074],"to":[8.287004,8.6147,7.1512504],"rotation":{"angle":0.0,"axis":"y","origin":[5.715575,8.18613,6.0083933]},"faces":{"east":{"uv":[6.0,0.5,6.375,0.75],"rotation":0,"texture":"#0","tintindex":0},"south":{"uv":[7.5,4.75,7.75,5.0],"rotation":0,"texture":"#0","tintindex":0},"north":{"uv":[7.5,4.5,7.75,4.75],"rotation":0,"texture":"#0","tintindex":0},"west":{"uv":[6.0,0.75,6.375,1.0],"rotation":0,"texture":"#0","tintindex":0},"up":{"uv":[1.25,6.375,1.0,6.0],"rotation":0,"texture":"#0","tintindex":0},"down":{"uv":[1.5,6.0,1.25,6.375],"rotation":0,"texture":"#0","tintindex":0}}},{"from":[7.7155757,9.043272,6.1512504],"to":[8.287004,9.18613,7.1512504],"rotation":{"angle":0.0,"axis":"y","origin":[5.715575,8.18613,6.0083933]},"faces":{"east":{"uv":[5.0,9.25,5.4375,9.3125],"rotation":0,"texture":"#0","tintindex":0},"south":{"uv":[1.25,9.75,1.5,9.8125],"rotation":0,"texture":"#0","tintindex":0},"north":{"uv":[9.75,1.0,10.0,1.0625],"rotation":0,"texture":"#0","tintindex":0},"west":{"uv":[9.25,5.0,9.6875,5.0625],"rotation":0,"texture":"#0","tintindex":0},"up":{"uv":[3.0,5.9375,2.75,5.5],"rotation":0,"texture":"#0","tintindex":0},"down":{"uv":[3.25,5.5,3.0,5.9375],"rotation":0,"texture":"#0","tintindex":0}}},{"from":[7.858433,8.900415,5.5798216],"to":[8.144147,9.043272,6.1512504],"rotation":{"angle":0.0,"axis":"y","origin":[5.715575,8.18613,6.0083933]},"faces":{"east":{"uv":[9.75,1.25,10.0,1.3125],"rotation":0,"texture":"#0","tintindex":0},"south":{"uv":[5.25,9.75,5.375,9.8125],"rotation":0,"texture":"#0","tintindex":0},"north":{"uv":[9.75,5.0,9.875,5.0625],"rotation":0,"texture":"#0","tintindex":0},"west":{"uv":[1.5,9.75,1.75,9.8125],"rotation":0,"texture":"#0","tintindex":0},"up":{"uv":[5.875,9.25,5.75,9.0],"rotation":0,"texture":"#0","tintindex":0},"down":{"uv":[9.125,5.75,9.0,6.0],"rotation":0,"texture":"#0","tintindex":0}}},{"from":[7.4298615,7.900415,6.2941074],"to":[7.4298615,8.6147,6.865536],"rotation":{"angle":45.0,"axis":"x","origin":[7.4298615,8.328986,6.5798216]},"faces":{"east":{"uv":[0.5,7.0,0.75,7.3125],"rotation":0,"texture":"#0","tintindex":0},"south":{"uv":[0.0,0.0,0.0,0.3125],"rotation":0,"texture":"#0","tintindex":0},"north":{"uv":[0.0,0.0,0.0,0.3125],"rotation":0,"texture":"#0","tintindex":0},"west":{"uv":[0.75,7.0,1.0,7.3125],"rotation":0,"texture":"#0","tintindex":0},"up":{"uv":[0.0,0.25,0.0,0.0],"rotation":0,"texture":"#0","tintindex":0},"down":{"uv":[0.0,0.0,0.0,0.25],"rotation":0,"texture":"#0","tintindex":0}}},{"from":[7.2870045,8.360675,5.7645216],"to":[8.715576,8.646389,6.6216645],"rotation":{"angle":-45.0,"axis":"x","origin":[8.858433,9.6147,6.2941074]},"faces":{"east":{"uv":[8.0,1.25,8.375,1.375],"rotation":0,"texture":"#0","tintindex":0},"south":{"uv":[7.0,1.25,7.625,1.375],"rotation":0,"texture":"#0","tintindex":0},"north":{"uv":[7.0,0.0,7.625,0.125],"rotation":0,"texture":"#0","tintindex":0},"west":{"uv":[8.0,1.5,8.375,1.625],"rotation":0,"texture":"#0","tintindex":0},"up":{"uv":[2.875,1.875,2.25,1.5],"rotation":0,"texture":"#0","tintindex":0},"down":{"uv":[2.875,2.0,2.25,2.375],"rotation":0,"texture":"#0","tintindex":0}}},{"from":[7.2870045,8.3534975,6.2349334],"to":[8.715576,8.639212,6.8063617],"rotation":{"angle":0.0,"axis":"y","origin":[5.715575,8.18613,6.0083933]},"faces":{"east":{"uv":[6.0,9.0,6.25,9.125],"rotation":0,"texture":"#0","tintindex":0},"south":{"uv":[7.0,1.5,7.625,1.625],"rotation":0,"texture":"#0","tintindex":0},"north":{"uv":[1.5,7.0,2.125,7.125],"rotation":0,"texture":"#0","tintindex":0},"west":{"uv":[9.0,6.0,9.25,6.125],"rotation":0,"texture":"#0","tintindex":0},"up":{"uv":[4.125,2.0,3.5,1.75],"rotation":0,"texture":"#0","tintindex":0},"down":{"uv":[4.125,2.0,3.5,2.25],"rotation":0,"texture":"#0","tintindex":0}}},{"from":[7.4298615,8.173003,5.8828673],"to":[7.858433,8.458718,6.454296],"rotation":{"angle":-45.0,"axis":"x","origin":[8.572719,8.284172,6.126739]},"faces":{"east":{"uv":[6.25,9.0,6.5,9.125],"rotation":0,"texture":"#0","tintindex":0},"south":{"uv":[9.25,9.0,9.4375,9.125],"rotation":0,"texture":"#0","tintindex":0},"north":{"uv":[9.0,9.25,9.1875,9.375],"rotation":0,"texture":"#0","tintindex":0},"west":{"uv":[9.0,6.25,9.25,6.375],"rotation":0,"texture":"#0","tintindex":0},"up":{"uv":[1.4375,8.25,1.25,8.0],"rotation":0,"texture":"#0","tintindex":0},"down":{"uv":[1.9375,8.0,1.75,8.25],"rotation":0,"texture":"#0","tintindex":0}}},{"from":[8.144147,8.173003,5.8828673],"to":[8.572719,8.458718,6.454296],"rotation":{"angle":-45.0,"axis":"x","origin":[7.4298615,8.284172,6.126739]},"faces":{"east":{"uv":[6.5,9.0,6.75,9.125],"rotation":0,"texture":"#0","tintindex":0},"south":{"uv":[0.0,9.5,0.1875,9.625],"rotation":0,"texture":"#0","tintindex":0},"north":{"uv":[9.25,9.25,9.4375,9.375],"rotation":0,"texture":"#0","tintindex":0},"west":{"uv":[9.0,6.5,9.25,6.625],"rotation":0,"texture":"#0","tintindex":0},"up":{"uv":[2.1875,8.25,2.0,8.0],"rotation":0,"texture":"#0","tintindex":0},"down":{"uv":[8.1875,2.0,8.0,2.25],"rotation":0,"texture":"#0","tintindex":0}}},{"from":[7.7155757,7.757558,6.1512504],"to":[8.287004,8.043272,7.1512504],"rotation":{"angle":0.0,"axis":"y","origin":[5.715575,8.18613,6.0083933]},"faces":{"east":{"uv":[2.5,7.75,2.9375,7.875],"rotation":0,"texture":"#0","tintindex":0},"south":{"uv":[9.0,6.75,9.25,6.875],"rotation":0,"texture":"#0","tintindex":0},"north":{"uv":[6.75,9.0,7.0,9.125],"rotation":0,"texture":"#0","tintindex":0},"west":{"uv":[7.75,2.5,8.1875,2.625],"rotation":0,"texture":"#0","tintindex":0},"up":{"uv":[5.75,3.4375,5.5,3.0],"rotation":0,"texture":"#0","tintindex":0},"down":{"uv":[3.5,5.5,3.25,5.9375],"rotation":0,"texture":"#0","tintindex":0}}},{"from":[7.858433,7.900415,5.15125],"to":[8.144147,8.043272,6.1512504],"rotation":{"angle":0.0,"axis":"y","origin":[5.715575,8.18613,6.0083933]},"faces":{"east":{"uv":[9.25,5.25,9.6875,5.3125],"rotation":0,"texture":"#0","tintindex":0},"south":{"uv":[5.5,9.75,5.625,9.8125],"rotation":0,"texture":"#0","tintindex":0},"north":{"uv":[9.75,5.25,9.875,5.3125],"rotation":0,"texture":"#0","tintindex":0},"west":{"uv":[5.5,9.25,5.9375,9.3125],"rotation":0,"texture":"#0","tintindex":0},"up":{"uv":[7.875,3.1875,7.75,2.75],"rotation":0,"texture":"#0","tintindex":0},"down":{"uv":[3.125,7.75,3.0,8.1875],"rotation":0,"texture":"#0","tintindex":0}}},{"from":[8.572719,7.900415,6.2941074],"to":[8.572719,8.6147,6.865536],"rotation":{"angle":45.0,"axis":"x","origin":[8.572719,8.328986,6.5798216]},"faces":{"east":{"uv":[2.25,7.0,2.5,7.3125],"rotation":0,"texture":"#0","tintindex":0},"south":{"uv":[0.0,0.0,0.0,0.3125],"rotation":0,"texture":"#0","tintindex":0},"north":{"uv":[0.0,0.0,0.0,0.3125],"rotation":0,"texture":"#0","tintindex":0},"west":{"uv":[2.5,7.0,2.75,7.3125],"rotation":0,"texture":"#0","tintindex":0},"up":{"uv":[0.0,0.25,0.0,0.0],"rotation":0,"texture":"#0","tintindex":0},"down":{"uv":[0.0,0.0,0.0,0.25],"rotation":0,"texture":"#0","tintindex":0}}},{"from":[7.858433,8.043272,4.8655357],"to":[8.144147,8.328986,5.4369645],"rotation":{"angle":0.0,"axis":"y","origin":[5.715575,8.18613,6.0083933]},"faces":{"east":{"uv":[7.0,9.0,7.25,9.125],"rotation":0,"texture":"#0","tintindex":0},"south":{"uv":[1.75,9.75,1.875,9.875],"rotation":0,"texture":"#0","tintindex":0},"north":{"uv":[9.75,1.5,9.875,1.625],"rotation":0,"texture":"#0","tintindex":0},"west":{"uv":[9.0,7.0,9.25,7.125],"rotation":0,"texture":"#0","tintindex":0},"up":{"uv":[7.375,9.25,7.25,9.0],"rotation":0,"texture":"#0","tintindex":0},"down":{"uv":[9.125,7.25,9.0,7.5],"rotation":0,"texture":"#0","tintindex":0}}},{"from":[7.5727186,8.043272,5.4369645],"to":[8.429861,8.900415,6.2941074],"rotation":{"angle":0.0,"axis":"y","origin":[5.715575,8.18613,6.0083933]},"faces":{"east":{"uv":[4.5,3.5,4.875,3.875],"rotation":0,"texture":"#0","tintindex":0},"south":{"uv":[4.0,4.5,4.375,4.875],"rotation":0,"texture":"#0","tintindex":0},"north":{"uv":[3.5,4.5,3.875,4.875],"rotation":0,"texture":"#0","tintindex":0},"west":{"uv":[4.5,4.0,4.875,4.375],"rotation":0,"texture":"#0","tintindex":0},"up":{"uv":[4.875,4.875,4.5,4.5],"rotation":0,"texture":"#0","tintindex":0},"down":{"uv":[0.375,4.75,0.0,5.125],"rotation":0,"texture":"#0","tintindex":0}}},{"from":[7.7155757,8.043272,5.15125],"to":[8.287004,8.6147,5.4369645],"rotation":{"angle":0.0,"axis":"y","origin":[5.715575,8.18613,6.0083933]},"faces":{"east":{"uv":[7.5,9.0,7.625,9.25],"rotation":0,"texture":"#0","tintindex":0},"south":{"uv":[5.25,7.5,5.5,7.75],"rotation":0,"texture":"#0","tintindex":0},"north":{"uv":[5.0,7.5,5.25,7.75],"rotation":0,"texture":"#0","tintindex":0},"west":{"uv":[9.0,7.5,9.125,7.75],"rotation":0,"texture":"#0","tintindex":0},"up":{"uv":[8.0,9.125,7.75,9.0],"rotation":0,"texture":"#0","tintindex":0},"down":{"uv":[9.25,7.75,9.0,7.875],"rotation":0,"texture":"#0","tintindex":0}}},{"from":[7.4298615,8.471844,6.0083933],"to":[8.572719,9.043272,7.1512504],"rotation":{"angle":0.0,"axis":"y","origin":[5.715575,8.18613,6.0083933]},"faces":{"east":{"uv":[5.25,1.5,5.75,1.75],"rotation":0,"texture":"#0","tintindex":0},"south":{"uv":[5.25,1.75,5.75,2.0],"rotation":0,"texture":"#0","tintindex":0},"north":{"uv":[1.5,5.25,2.0,5.5],"rotation":0,"texture":"#0","tintindex":0},"west":{"uv":[2.0,5.25,2.5,5.5],"rotation":0,"texture":"#0","tintindex":0},"up":{"uv":[2.0,0.5,1.5,0.0],"rotation":0,"texture":"#0","tintindex":0},"down":{"uv":[1.0,1.5,0.5,2.0],"rotation":0,"texture":"#0","tintindex":0}}},{"from":[7.5727186,8.328986,6.2941074],"to":[8.429861,8.900415,7.4369645],"rotation":{"angle":0.0,"axis":"y","origin":[5.715575,8.18613,6.0083933]},"faces":{"east":{"uv":[5.25,2.0,5.75,2.25],"rotation":0,"texture":"#0","tintindex":0},"south":{"uv":[1.5,6.0,1.875,6.25],"rotation":0,"texture":"#0","tintindex":0},"north":{"uv":[6.0,1.0,6.375,1.25],"rotation":0,"texture":"#0","tintindex":0},"west":{"uv":[5.25,2.25,5.75,2.5],"rotation":0,"texture":"#0","tintindex":0},"up":{"uv":[2.875,3.5,2.5,3.0],"rotation":0,"texture":"#0","tintindex":0},"down":{"uv":[3.375,2.5,3.0,3.0],"rotation":0,"texture":"#0","tintindex":0}}},{"from":[7.7155757,8.043272,6.2941074],"to":[8.287004,8.6147,7.1512504],"rotation":{"angle":0.0,"axis":"y","origin":[5.715575,8.18613,6.0083933]},"faces":{"east":{"uv":[2.0,6.0,2.375,6.25],"rotation":0,"texture":"#0","tintindex":0},"south":{"uv":[7.5,5.5,7.75,5.75],"rotation":0,"texture":"#0","tintindex":0},"north":{"uv":[5.5,7.5,5.75,7.75],"rotation":0,"texture":"#0","tintindex":0},"west":{"uv":[2.5,6.0,2.875,6.25],"rotation":0,"texture":"#0","tintindex":0},"up":{"uv":[6.25,3.125,6.0,2.75],"rotation":0,"texture":"#0","tintindex":0},"down":{"uv":[3.25,6.0,3.0,6.375],"rotation":0,"texture":"#0","tintindex":0}}},{"from":[7.7155757,9.043272,6.1512504],"to":[8.287004,9.18613,7.1512504],"rotation":{"angle":0.0,"axis":"y","origin":[5.715575,8.18613,6.0083933]},"faces":{"east":{"uv":[9.25,5.5,9.6875,5.5625],"rotation":0,"texture":"#0","tintindex":0},"south":{"uv":[2.0,9.75,2.25,9.8125],"rotation":0,"texture":"#0","tintindex":0},"north":{"uv":[9.75,1.75,10.0,1.8125],"rotation":0,"texture":"#0","tintindex":0},"west":{"uv":[9.25,5.75,9.6875,5.8125],"rotation":0,"texture":"#0","tintindex":0},"up":{"uv":[3.75,5.9375,3.5,5.5],"rotation":0,"texture":"#0","tintindex":0},"down":{"uv":[5.75,3.5,5.5,3.9375],"rotation":0,"texture":"#0","tintindex":0}}},{"from":[7.858433,8.900415,5.5798216],"to":[8.144147,9.043272,6.1512504],"rotation":{"angle":0.0,"axis":"y","origin":[5.715575,8.18613,6.0083933]},"faces":{"east":{"uv":[9.75,2.0,10.0,2.0625],"rotation":0,"texture":"#0","tintindex":0},"south":{"uv":[5.75,9.75,5.875,9.8125],"rotation":0,"texture":"#0","tintindex":0},"north":{"uv":[9.75,5.5,9.875,5.5625],"rotation":0,"texture":"#0","tintindex":0},"west":{"uv":[2.25,9.75,2.5,9.8125],"rotation":0,"texture":"#0","tintindex":0},"up":{"uv":[8.125,9.25,8.0,9.0],"rotation":0,"texture":"#0","tintindex":0},"down":{"uv":[9.125,8.0,9.0,8.25],"rotation":0,"texture":"#0","tintindex":0}}},{"from":[7.4298615,7.900415,6.2941074],"to":[7.4298615,8.6147,6.865536],"rotation":{"angle":45.0,"axis":"x","origin":[7.4298615,8.328986,6.5798216]},"faces":{"east":{"uv":[7.0,2.5,7.25,2.8125],"rotation":0,"texture":"#0","tintindex":0},"south":{"uv":[0.0,0.0,0.0,0.3125],"rotation":0,"texture":"#0","tintindex":0},"north":{"uv":[0.0,0.0,0.0,0.3125],"rotation":0,"texture":"#0","tintindex":0},"west":{"uv":[2.75,7.0,3.0,7.3125],"rotation":0,"texture":"#0","tintindex":0},"up":{"uv":[0.0,0.25,0.0,0.0],"rotation":0,"texture":"#0","tintindex":0},"down":{"uv":[0.0,0.0,0.0,0.25],"rotation":0,"texture":"#0","tintindex":0}}},{"from":[7.2870045,8.360675,5.7645216],"to":[8.715576,8.646389,6.6216645],"rotation":{"angle":-45.0,"axis":"x","origin":[8.858433,9.6147,6.2941074]},"faces":{"east":{"uv":[8.0,2.25,8.375,2.375],"rotation":0,"texture":"#0","tintindex":0},"south":{"uv":[7.0,3.0,7.625,3.125],"rotation":0,"texture":"#0","tintindex":0},"north":{"uv":[3.0,7.0,3.625,7.125],"rotation":0,"texture":"#0","tintindex":0},"west":{"uv":[2.5,8.0,2.875,8.125],"rotation":0,"texture":"#0","tintindex":0},"up":{"uv":[0.625,2.875,0.0,2.5],"rotation":0,"texture":"#0","tintindex":0},"down":{"uv":[1.375,2.5,0.75,2.875],"rotation":0,"texture":"#0","tintindex":0}}},{"from":[7.2870045,8.3534975,6.2349334],"to":[8.715576,8.639212,6.8063617],"rotation":{"angle":0.0,"axis":"y","origin":[5.715575,8.18613,6.0083933]},"faces":{"east":{"uv":[8.25,9.0,8.5,9.125],"rotation":0,"texture":"#0","tintindex":0},"south":{"uv":[7.0,3.5,7.625,3.625],"rotation":0,"texture":"#0","tintindex":0},"north":{"uv":[7.0,3.25,7.625,3.375],"rotation":0,"texture":"#0","tintindex":0},"west":{"uv":[9.0,8.25,9.25,8.375],"rotation":0,"texture":"#0","tintindex":0},"up":{"uv":[2.875,3.75,2.25,3.5],"rotation":0,"texture":"#0","tintindex":0},"down":{"uv":[4.125,2.25,3.5,2.5],"rotation":0,"texture":"#0","tintindex":0}}},{"from":[7.4298615,8.173003,5.8828673],"to":[7.858433,8.458718,6.454296],"rotation":{"angle":-45.0,"axis":"x","origin":[8.572719,8.284172,6.126739]},"faces":{"east":{"uv":[8.5,9.0,8.75,9.125],"rotation":0,"texture":"#0","tintindex":0},"south":{"uv":[0.25,9.5,0.4375,9.625],"rotation":0,"texture":"#0","tintindex":0},"north":{"uv":[9.5,0.0,9.6875,0.125],"rotation":0,"texture":"#0","tintindex":0},"west":{"uv":[9.0,8.5,9.25,8.625],"rotation":0,"texture":"#0","tintindex":0},"up":{"uv":[8.1875,3.0,8.0,2.75],"rotation":0,"texture":"#0","tintindex":0},"down":{"uv":[8.1875,3.0,8.0,3.25],"rotation":0,"texture":"#0","tintindex":0}}},{"from":[8.144147,8.173003,5.8828673],"to":[8.572719,8.458718,6.454296],"rotation":{"angle":-45.0,"axis":"x","origin":[7.4298615,8.284172,6.126739]},"faces":{"east":{"uv":[8.75,9.0,9.0,9.125],"rotation":0,"texture":"#0","tintindex":0},"south":{"uv":[0.5,9.5,0.6875,9.625],"rotation":0,"texture":"#0","tintindex":0},"north":{"uv":[9.5,0.25,9.6875,0.375],"rotation":0,"texture":"#0","tintindex":0},"west":{"uv":[9.0,8.75,9.25,8.875],"rotation":0,"texture":"#0","tintindex":0},"up":{"uv":[3.4375,8.25,3.25,8.0],"rotation":0,"texture":"#0","tintindex":0},"down":{"uv":[3.6875,8.0,3.5,8.25],"rotation":0,"texture":"#0","tintindex":0}}},{"from":[7.7155757,7.757558,6.1512504],"to":[8.287004,8.043272,7.1512504],"rotation":{"angle":0.0,"axis":"y","origin":[5.715575,8.18613,6.0083933]},"faces":{"east":{"uv":[3.25,7.75,3.6875,7.875],"rotation":0,"texture":"#0","tintindex":0},"south":{"uv":[0.0,9.25,0.25,9.375],"rotation":0,"texture":"#0","tintindex":0},"north":{"uv":[9.0,9.0,9.25,9.125],"rotation":0,"texture":"#0","tintindex":0},"west":{"uv":[7.75,3.25,8.1875,3.375],"rotation":0,"texture":"#0","tintindex":0},"up":{"uv":[4.0,5.9375,3.75,5.5],"rotation":0,"texture":"#0","tintindex":0},"down":{"uv":[4.25,5.5,4.0,5.9375],"rotation":0,"texture":"#0","tintindex":0}}},{"from":[7.858433,7.900415,5.15125],"to":[8.144147,8.043272,6.1512504],"rotation":{"angle":0.0,"axis":"y","origin":[5.715575,8.18613,6.0083933]},"faces":{"east":{"uv":[6.0,9.25,6.4375,9.3125],"rotation":0,"texture":"#0","tintindex":0},"south":{"uv":[6.0,9.75,6.125,9.8125],"rotation":0,"texture":"#0","tintindex":0},"north":{"uv":[9.75,5.75,9.875,5.8125],"rotation":0,"texture":"#0","tintindex":0},"west":{"uv":[9.25,6.0,9.6875,6.0625],"rotation":0,"texture":"#0","tintindex":0},"up":{"uv":[7.875,3.9375,7.75,3.5],"rotation":0,"texture":"#0","tintindex":0},"down":{"uv":[3.875,7.75,3.75,8.1875],"rotation":0,"texture":"#0","tintindex":0}}},{"from":[8.572719,7.900415,6.2941074],"to":[8.572719,8.6147,6.865536],"rotation":{"angle":45.0,"axis":"x","origin":[8.572719,8.328986,6.5798216]},"faces":{"east":{"uv":[3.75,7.0,4.0,7.3125],"rotation":0,"texture":"#0","tintindex":0},"south":{"uv":[0.0,0.0,0.0,0.3125],"rotation":0,"texture":"#0","tintindex":0},"north":{"uv":[0.0,0.0,0.0,0.3125],"rotation":0,"texture":"#0","tintindex":0},"west":{"uv":[7.0,3.75,7.25,4.0625],"rotation":0,"texture":"#0","tintindex":0},"up":{"uv":[0.0,0.25,0.0,0.0],"rotation":0,"texture":"#0","tintindex":0},"down":{"uv":[0.0,0.0,0.0,0.25],"rotation":0,"texture":"#0","tintindex":0}}},{"from":[7.858433,8.043272,4.8655357],"to":[8.144147,8.328986,5.4369645],"rotation":{"angle":0.0,"axis":"y","origin":[5.715575,8.18613,6.0083933]},"faces":{"east":{"uv":[9.25,0.0,9.5,0.125],"rotation":0,"texture":"#0","tintindex":0},"south":{"uv":[2.5,9.75,2.625,9.875],"rotation":0,"texture":"#0","tintindex":0},"north":{"uv":[9.75,2.25,9.875,2.375],"rotation":0,"texture":"#0","tintindex":0},"west":{"uv":[0.25,9.25,0.5,9.375],"rotation":0,"texture":"#0","tintindex":0},"up":{"uv":[9.375,0.5,9.25,0.25],"rotation":0,"texture":"#0","tintindex":0},"down":{"uv":[0.625,9.25,0.5,9.5],"rotation":0,"texture":"#0","tintindex":0}}},{"from":[7.5727186,8.043272,5.4369645],"to":[8.429861,8.900415,6.2941074],"rotation":{"angle":0.0,"axis":"y","origin":[5.715575,8.18613,6.0083933]},"faces":{"east":{"uv":[0.5,4.75,0.875,5.125],"rotation":0,"texture":"#0","tintindex":0},"south":{"uv":[1.0,4.75,1.375,5.125],"rotation":0,"texture":"#0","tintindex":0},"north":{"uv":[4.75,0.0,5.125,0.375],"rotation":0,"texture":"#0","tintindex":0},"west":{"uv":[4.75,1.0,5.125,1.375],"rotation":0,"texture":"#0","tintindex":0},"up":{"uv":[1.875,5.125,1.5,4.75],"rotation":0,"texture":"#0","tintindex":0},"down":{"uv":[5.125,1.5,4.75,1.875],"rotation":0,"texture":"#0","tintindex":0}}},{"from":[7.7155757,8.043272,5.15125],"to":[8.287004,8.6147,5.4369645],"rotation":{"angle":0.0,"axis":"y","origin":[5.715575,8.18613,6.0083933]},"faces":{"east":{"uv":[9.25,0.5,9.375,0.75],"rotation":0,"texture":"#0","tintindex":0},"south":{"uv":[7.5,6.0,7.75,6.25],"rotation":0,"texture":"#0","tintindex":0},"north":{"uv":[7.5,5.75,7.75,6.0],"rotation":0,"texture":"#0","tintindex":0},"west":{"uv":[0.75,9.25,0.875,9.5],"rotation":0,"texture":"#0","tintindex":0},"up":{"uv":[9.5,0.875,9.25,0.75],"rotation":0,"texture":"#0","tintindex":0},"down":{"uv":[1.25,9.25,1.0,9.375],"rotation":0,"texture":"#0","tintindex":0}}},{"from":[7.4298615,8.471844,6.0083933],"to":[8.572719,9.043272,7.1512504],"rotation":{"angle":0.0,"axis":"y","origin":[5.715575,8.18613,6.0083933]},"faces":{"east":{"uv":[5.25,2.5,5.75,2.75],"rotation":0,"texture":"#0","tintindex":0},"south":{"uv":[5.25,2.75,5.75,3.0],"rotation":0,"texture":"#0","tintindex":0},"north":{"uv":[2.5,5.25,3.0,5.5],"rotation":0,"texture":"#0","tintindex":0},"west":{"uv":[3.0,5.25,3.5,5.5],"rotation":0,"texture":"#0","tintindex":0},"up":{"uv":[2.0,1.0,1.5,0.5],"rotation":0,"texture":"#0","tintindex":0},"down":{"uv":[1.5,1.5,1.0,2.0],"rotation":0,"texture":"#0","tintindex":0}}},{"from":[7.5727186,8.328986,6.2941074],"to":[8.429861,8.900415,7.4369645],"rotation":{"angle":0.0,"axis":"y","origin":[5.715575,8.18613,6.0083933]},"faces":{"east":{"uv":[3.5,5.25,4.0,5.5],"rotation":0,"texture":"#0","tintindex":0},"south":{"uv":[6.0,3.25,6.375,3.5],"rotation":0,"texture":"#0","tintindex":0},"north":{"uv":[3.25,6.0,3.625,6.25],"rotation":0,"texture":"#0","tintindex":0},"west":{"uv":[4.0,5.25,4.5,5.5],"rotation":0,"texture":"#0","tintindex":0},"up":{"uv":[3.375,3.5,3.0,3.0],"rotation":0,"texture":"#0","tintindex":0},"down":{"uv":[3.625,0.0,3.25,0.5],"rotation":0,"texture":"#0","tintindex":0}}},{"from":[7.7155757,8.043272,6.2941074],"to":[8.287004,8.6147,7.1512504],"rotation":{"angle":0.0,"axis":"y","origin":[5.715575,8.18613,6.0083933]},"faces":{"east":{"uv":[6.0,3.5,6.375,3.75],"rotation":0,"texture":"#0","tintindex":0},"south":{"uv":[6.5,7.5,6.75,7.75],"rotation":0,"texture":"#0","tintindex":0},"north":{"uv":[6.25,7.5,6.5,7.75],"rotation":0,"texture":"#0","tintindex":0},"west":{"uv":[3.75,6.0,4.125,6.25],"rotation":0,"texture":"#0","tintindex":0},"up":{"uv":[4.5,6.375,4.25,6.0],"rotation":0,"texture":"#0","tintindex":0},"down":{"uv":[4.75,6.0,4.5,6.375],"rotation":0,"texture":"#0","tintindex":0}}},{"from":[7.7155757,9.043272,6.1512504],"to":[8.287004,9.18613,7.1512504],"rotation":{"angle":0.0,"axis":"y","origin":[5.715575,8.18613,6.0083933]},"faces":{"east":{"uv":[9.25,6.25,9.6875,6.3125],"rotation":0,"texture":"#0","tintindex":0},"south":{"uv":[2.75,9.75,3.0,9.8125],"rotation":0,"texture":"#0","tintindex":0},"north":{"uv":[9.75,2.5,10.0,2.5625],"rotation":0,"texture":"#0","tintindex":0},"west":{"uv":[6.5,9.25,6.9375,9.3125],"rotation":0,"texture":"#0","tintindex":0},"up":{"uv":[5.75,4.4375,5.5,4.0],"rotation":0,"texture":"#0","tintindex":0},"down":{"uv":[4.5,5.5,4.25,5.9375],"rotation":0,"texture":"#0","tintindex":0}}},{"from":[7.858433,8.900415,5.5798216],"to":[8.144147,9.043272,6.1512504],"rotation":{"angle":0.0,"axis":"y","origin":[5.715575,8.18613,6.0083933]},"faces":{"east":{"uv":[9.75,2.75,10.0,2.8125],"rotation":0,"texture":"#0","tintindex":0},"south":{"uv":[6.25,9.75,6.375,9.8125],"rotation":0,"texture":"#0","tintindex":0},"north":{"uv":[9.75,6.0,9.875,6.0625],"rotation":0,"texture":"#0","tintindex":0},"west":{"uv":[3.0,9.75,3.25,9.8125],"rotation":0,"texture":"#0","tintindex":0},"up":{"uv":[9.375,1.25,9.25,1.0],"rotation":0,"texture":"#0","tintindex":0},"down":{"uv":[1.375,9.25,1.25,9.5],"rotation":0,"texture":"#0","tintindex":0}}},{"from":[7.4298615,7.900415,6.2941074],"to":[7.4298615,8.6147,6.865536],"rotation":{"angle":45.0,"axis":"x","origin":[7.4298615,8.328986,6.5798216]},"faces":{"east":{"uv":[4.0,7.0,4.25,7.3125],"rotation":0,"texture":"#0","tintindex":0},"south":{"uv":[0.0,0.0,0.0,0.3125],"rotation":0,"texture":"#0","tintindex":0},"north":{"uv":[0.0,0.0,0.0,0.3125],"rotation":0,"texture":"#0","tintindex":0},"west":{"uv":[5.0,7.0,5.25,7.3125],"rotation":0,"texture":"#0","tintindex":0},"up":{"uv":[0.0,0.25,0.0,0.0],"rotation":0,"texture":"#0","tintindex":0},"down":{"uv":[0.0,0.0,0.0,0.25],"rotation":0,"texture":"#0","tintindex":0}}},{"from":[7.2870045,8.360675,5.7645216],"to":[8.715576,8.646389,6.6216645],"rotation":{"angle":-45.0,"axis":"x","origin":[8.858433,9.6147,6.2941074]},"faces":{"east":{"uv":[8.0,3.5,8.375,3.625],"rotation":0,"texture":"#0","tintindex":0},"south":{"uv":[7.0,5.25,7.625,5.375],"rotation":0,"texture":"#0","tintindex":0},"north":{"uv":[5.25,7.0,5.875,7.125],"rotation":0,"texture":"#0","tintindex":0},"west":{"uv":[8.0,3.75,8.375,3.875],"rotation":0,"texture":"#0","tintindex":0},"up":{"uv":[2.125,2.875,1.5,2.5],"rotation":0,"texture":"#0","tintindex":0},"down":{"uv":[2.875,2.5,2.25,2.875],"rotation":0,"texture":"#0","tintindex":0}}},{"from":[7.2870045,8.3534975,6.2349334],"to":[8.715576,8.639212,6.8063617],"rotation":{"angle":0.0,"axis":"y","origin":[5.715575,8.18613,6.0083933]},"faces":{"east":{"uv":[9.25,1.25,9.5,1.375],"rotation":0,"texture":"#0","tintindex":0},"south":{"uv":[7.0,6.5,7.625,6.625],"rotation":0,"texture":"#0","tintindex":0},"north":{"uv":[6.0,7.0,6.625,7.125],"rotation":0,"texture":"#0","tintindex":0},"west":{"uv":[1.5,9.25,1.75,9.375],"rotation":0,"texture":"#0","tintindex":0},"up":{"uv":[4.125,2.75,3.5,2.5],"rotation":0,"texture":"#0","tintindex":0},"down":{"uv":[4.125,2.75,3.5,3.0],"rotation":0,"texture":"#0","tintindex":0}}},{"from":[7.4298615,8.173003,5.8828673],"to":[7.858433,8.458718,6.454296],"rotation":{"angle":-45.0,"axis":"x","origin":[8.572719,8.284172,6.126739]},"faces":{"east":{"uv":[9.25,1.5,9.5,1.625],"rotation":0,"texture":"#0","tintindex":0},"south":{"uv":[0.75,9.5,0.9375,9.625],"rotation":0,"texture":"#0","tintindex":0},"north":{"uv":[9.5,0.5,9.6875,0.625],"rotation":0,"texture":"#0","tintindex":0},"west":{"uv":[1.75,9.25,2.0,9.375],"rotation":0,"texture":"#0","tintindex":0},"up":{"uv":[4.1875,8.25,4.0,8.0],"rotation":0,"texture":"#0","tintindex":0},"down":{"uv":[4.4375,8.0,4.25,8.25],"rotation":0,"texture":"#0","tintindex":0}}},{"from":[8.144147,8.173003,5.8828673],"to":[8.572719,8.458718,6.454296],"rotation":{"angle":-45.0,"axis":"x","origin":[7.4298615,8.284172,6.126739]},"faces":{"east":{"uv":[9.25,1.75,9.5,1.875],"rotation":0,"texture":"#0","tintindex":0},"south":{"uv":[1.0,9.5,1.1875,9.625],"rotation":0,"texture":"#0","tintindex":0},"north":{"uv":[9.5,0.75,9.6875,0.875],"rotation":0,"texture":"#0","tintindex":0},"west":{"uv":[2.0,9.25,2.25,9.375],"rotation":0,"texture":"#0","tintindex":0},"up":{"uv":[8.1875,4.5,8.0,4.25],"rotation":0,"texture":"#0","tintindex":0},"down":{"uv":[8.1875,4.5,8.0,4.75],"rotation":0,"texture":"#0","tintindex":0}}},{"from":[7.7155757,7.757558,6.1512504],"to":[8.287004,8.043272,7.1512504],"rotation":{"angle":0.0,"axis":"y","origin":[5.715575,8.18613,6.0083933]},"faces":{"east":{"uv":[4.0,7.75,4.4375,7.875],"rotation":0,"texture":"#0","tintindex":0},"south":{"uv":[2.25,9.25,2.5,9.375],"rotation":0,"texture":"#0","tintindex":0},"north":{"uv":[9.25,2.0,9.5,2.125],"rotation":0,"texture":"#0","tintindex":0},"west":{"uv":[7.75,4.0,8.1875,4.125],"rotation":0,"texture":"#0","tintindex":0},"up":{"uv":[5.75,4.9375,5.5,4.5],"rotation":0,"texture":"#0","tintindex":0},"down":{"uv":[5.75,5.0,5.5,5.4375],"rotation":0,"texture":"#0","tintindex":0}}},{"from":[7.858433,7.900415,5.15125],"to":[8.144147,8.043272,6.1512504],"rotation":{"angle":0.0,"axis":"y","origin":[5.715575,8.18613,6.0083933]},"faces":{"east":{"uv":[9.25,6.5,9.6875,6.5625],"rotation":0,"texture":"#0","tintindex":0},"south":{"uv":[6.5,9.75,6.625,9.8125],"rotation":0,"texture":"#0","tintindex":0},"north":{"uv":[9.75,6.25,9.875,6.3125],"rotation":0,"texture":"#0","tintindex":0},"west":{"uv":[9.25,6.75,9.6875,6.8125],"rotation":0,"texture":"#0","tintindex":0},"up":{"uv":[7.875,4.6875,7.75,4.25],"rotation":0,"texture":"#0","tintindex":0},"down":{"uv":[4.625,7.75,4.5,8.1875],"rotation":0,"texture":"#0","tintindex":0}}}],"display":{"head":{"translation":[0.0,-6.4,0.0],"scale":[4.0,4.0,4.0]}}}
